Workbook
Name bpx_eigenkapitalquote: Stuetzstellen!$A$6:$A$13
Name bpy_eigenkapitalquote: Stuetzstellen!$B$6:$B$13
Name bpx_kapitaldienstfaehigkeit_inkl_neu: Stuetzstellen!$A$17:$A$24
Name bpy_kapitaldienstfaehigkeit_inkl_neu: Stuetzstellen!$B$17:$B$24
Name bpx_dynamischer_verschuldungsgrad: Stuetzstellen!$A$28:$A$37
Name bpy_dynamischer_verschuldungsgrad: Stuetzstellen!$B$28:$B$37
Name bpx_ebit_marge: Stuetzstellen!$A$41:$A$49
Name bpy_ebit_marge: Stuetzstellen!$B$41:$B$49
Name bpx_liquiditaet_2_grades: Stuetzstellen!$A$53:$A$60
Name bpy_liquiditaet_2_grades: Stuetzstellen!$B$53:$B$60
Name bpx_zinsdeckungsgrad: Stuetzstellen!$A$64:$A$70
Name bpy_zinsdeckungsgrad: Stuetzstellen!$B$64:$B$70
Name bpx_kontokorrent_auslastung: Stuetzstellen!$A$74:$A$81
Name bpy_kontokorrent_auslastung: Stuetzstellen!$B$74:$B$81
Name bpx_bwa_age_months: Stuetzstellen!$A$85:$A$91
Name bpy_bwa_age_months: Stuetzstellen!$B$85:$B$91
Name bpx_creditreform_bonitaetsindex: Stuetzstellen!$A$95:$A$103
Name bpy_creditreform_bonitaetsindex: Stuetzstellen!$B$95:$B$103
Name bpx_zahlungsverhalten: Stuetzstellen!$A$107:$A$108
Name bpy_zahlungsverhalten: Stuetzstellen!$B$107:$B$108

Sheet Anleitung
A1: Scorecard-Pruefblatt
A3: Wozu dieses Blatt / What this workbook is for
A4: Es rechnet die Bewertung der Engine mit Excel-Formeln nach. Jede Zahl ist nachvollziehbar,
A5: keine Zelle ist ein exportiertes Ergebnis. Wer die Engine pruefen will, prueft sie hier.
A7: It reimplements the engine's scoring in live Excel formulas. Nothing is a pasted result.
A9: So benutzen Sie es / How to use it
A10: 1. Blatt 'Eingaben': Spalte C ist Ihr eigener Fall. Ueberschreiben Sie die Werte.
A11: Spalten D bis I sind die Musterfaelle und sollten unveraendert bleiben.
A12: 2. Blatt 'Kennzahlen': alle Zwischengroessen und Kennzahlen, Formel fuer Formel.
A13: 3. Blatt 'Scorecard': die zehn Faktoren, ihre Punkte, Gewichte, der Gesamtscore und das Band.
A14: 4. Blatt 'Abgleich': Excel gegen Engine, Faktor fuer Faktor, fuer jeden Musterfall.
A15: Dort muss ueberall 'OK' stehen. Steht dort eine Abweichung, ist eine der beiden Seiten falsch.
... A30: Bei jeder Aenderung an scorecard.py oder ratios.py neu erzeugen.

Sheet Stuetzstellen
A1: Stuetzstellen der Faktoren / factor breakpoints
A2: Zwischen den Punkten wird linear interpoliert, ausserhalb wird gekappt.
A4: Eigenkapitalquote (wirtschaftlich) | C4: Gewicht 20% | D4: Wirtschaftliches EK inkl. nachrangiger Gesellschafterdarlehen. Stuetzstellen 14,8/35,1/56,9% = Quartile der Bundesbank-Statistik.
A5: Wert | B5: Punkte
A6: -0.2 | B6: 0
A7: 0 | B7: 25
A8: 0.05 | B8: 38
A9: 0.148 | B9: 58
A10: 0.351 | B10: 70
A11: 0.569 | B11: 82
A12: 0.8 | B12: 95
A13: 1 | B13: 100
A15: Kapitaldienstfaehigkeit inkl. neuer Finanzierung (DSCR) | C15: Gewicht 20% | D15: EBITDA / (Zins + Tilgung), inkl. des beantragten Engagements.
A16: Wert | B16: Punkte
A17: 0.7 | B17: 0
A18: 0.9 | B18: 12
A19: 1 | B19: 25
A20: 1.1 | B20: 42
A21: 1.2 | B21: 58
A22: 1.3 | B22: 72
A23: 1.5 | B23: 88
A24: 2 | B24: 100
A26: Dynamischer Verschuldungsgrad (Nettoverschuldung / EBITDA) | C26: Gewicht 15%
A27: Wert | B27: Punkte
A28: 0 | B28: 100
A29: 1 | B29: 95
A30: 2 | B30: 88
A31: 3 | B31: 75
A32: 3.5 | B32: 65
A33: 4 | B33: 55
A34: 5 | B34: 38
A35: 6 | B35: 25
A36: 8 | B36: 10
A37: 12 | B37: 0
A39: EBIT-Marge | C39: Gewicht 12% | D39: Stuetzstellen 1,35/4,75/9,95% = Bundesbank-Quartile des Ergebnisses vor Steuern, um 0,5 Punkte auf EBIT-Basis angehoben.
A40: Wert | B40: Punkte
A41: -0.1 | B41: 0
A42: -0.05 | B42: 12
A43: -0.02 | B43: 28
A44: 0 | B44: 45
A45: 0.0135 | B45: 58
A46: 0.0475 | B46: 70
A47: 0.0995 | B47: 82
A48: 0.18 | B48: 95
A49: 0.25 | B49: 100
A51: Liquiditaet 2. Grades | C51: Gewicht 8% | D51: Stuetzstellen 45,8/91,7/216,3% = Quartile der Bundesbank-Statistik.
A52: Wert | B52: Punkte
A53: 0 | B53: 0
A54: 0.2 | B54: 25
A55: 0.3 | B55: 40
A56: 0.458 | B56: 58
A57: 0.917 | B57: 70
A58: 2.163 | B58: 82
A59: 4 | B59: 95
A60: 6 | B60: 100
A62: Zinsdeckungsgrad (EBIT / Zinsaufwand) | C62: Gewicht 5%
A63: Wert | B63: Punkte
A64: 0 | B64: 0
A65: 1 | B65: 20
A66: 1.5 | B66: 35
A67: 2 | B67: 50
A68: 3 | B68: 70
A69: 5 | B69: 88
A70: 8 | B70: 100
A72: Kontokorrent-Auslastung | C72: Gewicht 6% | D72: Dauerhafte Ausschoepfung >80% gilt als klassisches Warnsignal.
A73: Wert | B73: Punkte
A74: 0 | B74: 100
A75: 0.3 | B75: 92
A76: 0.5 | B76: 80
A77: 0.7 | B77: 62
A78: 0.8 | B78: 45
A79: 0.9 | B79: 28
A80: 1 | B80: 10
A81: 1.1 | B81: 0
A83: Aktualitaet der BWA | C83: Gewicht 5%
A84: Wert | B84: Punkte
A85: 1 | B85: 100
A86: 2 | B86: 90
A87: 3 | B87: 72
A88: 4 | B88: 55
A89: 6 | B89: 32
A90: 9 | B90: 12
A91: 12 | B91: 0
A93: Creditreform Bonitaetsindex | C93: Gewicht 5%
A94: Wert | B94: Punkte
A95: 100 | B95: 100
A96: 150 | B96: 95
A97: 200 | B97: 85
A98: 250 | B98: 72
A99: 300 | B99: 55
A100: 350 | B100: 35
A101: 400 | B101: 18
A102: 500 | B102: 5
A103: 600 | B103: 0
A105: Zahlungsverhalten | C105: Gewicht 4% | D105: Aggregat aus Zahlungsverzug, Ruecklastschriften, Steuerrueckstaenden.
A106: Wert | B106: Punkte
A107: 0 | B107: 0
A108: 100 | B108: 100
A110: Bandgrenzen / band thresholds
A111: Score >= 78 | B111: A | C111: Voraussichtlich zu Standardkonditionen finanzierbar
...

Sheet Eingaben
A1: Eingaben / inputs
A2: Spalte C ueberschreiben. Musterfaelle nicht aendern -- der Abgleich haengt daran.
A4: Position | B4: Hinweis / note | C4: Ihr Fall | D4: Mueller Praezisionstechnik GmbH | E4: Nordlicht Handel GmbH & Co. KG | F4: Gastro Rheinblick GmbH | G4: Datenwerk Consulting GmbH | H4: Ihrig Sanitaer- und Heizungstechnik GmbH | I4: Hoffmann Medizintechnik GmbH
A5: AKTIVA (Bilanz, HGB §266) | B5: Assets
A6: Immaterielle Vermoegensgegenstaende | B6: Intangibles incl. goodwill | C6: 60000 | D6: 60000 | E6: 0 | F6: 180000 | G6: 95000 | H6: 0 | I6: 140000
A7: Sachanlagen | B7: Tangible fixed assets | C7: 2100000 | D7: 2100000 | E7: 420000 | F7: 1450000 | G7: 210000 | H7: 1000000 | I7: 3200000
A8: Finanzanlagen | B8: Financial assets | C8: 0 | D8: 0 | E8: 0 | F8: 0 | G8: 0 | H8: 0 | I8: 260000
A9: Vorraete | B9: Inventory | C9: 780000 | D9: 780000 | E9: 1850000 | F9: 85000 | G9: 0 | H9: 240000 | I9: 1180000
A10: Forderungen aus L+L | B10: Trade receivables | C10: 1150000 | D10: 1150000 | E10: 2240000 | F10: 45000 | G10: 1420000 | H10: 520000 | I10: 1340000
A11: Sonstige Vermoegensgegenstaende | B11: Other assets | C11: 90000 | D11: 90000 | E11: 70000 | F11: 0 | G11: 85000 | H11: 0 | I11: 0
A12: Wertpapiere | B12: Securities | C12: 0 | D12: 0 | E12: 0 | F12: 0 | G12: 0 | H12: 0 | I12: 0
A13: Liquide Mittel | B13: Cash and bank | C13: 180000 | D13: 180000 | E13: 60000 | F13: 22000 | G13: 640000 | H13: 310000 | I13: 1850000
A14: Aktive Rechnungsabgrenzung | B14: Prepaid expenses | C14: 25000 | D14: 25000 | E14: 0 | F14: 0 | G14: 0 | H14: 0 | I14: 0
A15: PASSIVA (Bilanz) | B15: Liabilities and equity
A16: Gezeichnetes Kapital | B16: Subscribed capital | C16: 25000 | D16: 25000 | E16: 50000 | F16: 25000 | G16: 50000 | H16: 25000 | I16: 200000
A17: Kapitalruecklage | B17: Capital reserve | C17: 0 | D17: 0 | E17: 0 | F17: 0 | G17: 150000 | H17: 0 | I17: 400000
A18: Gewinnruecklagen | B18: Retained earnings reserve | C18: 95000 | D18: 95000 | E18: 220000 | F18: 0 | G18: 320000 | H18: 232000 | I18: 2763000
A19: Gewinnvortrag / Verlustvortrag | B19: Profit carried forward (may be negative) | C19: 95000 | D19: 95000 | E19: 130000 | F19: -137000 | G19: 260000 | H19: 140000 | I19: 610000
A20: Jahresueberschuss laut Bilanz | B20: Net result as shown in equity | C20: 230000 | D20: 230000 | E20: 116000 | F20: -458000 | G20: 485000 | H20: 96000 | I20: 967000
A21: Ausstehende Einlagen | B21: Unpaid contributions (deducted) | C21: 0 | D21: 0 | E21: 0 | F21: 0 | G21: 0 | H21: 0 | I21: 0
A22: Rueckstellungen | B22: Provisions | C22: 350000 | D22: 350000 | E22: 145000 | F22: 120000 | G22: 285000 | H22: 165000 | I22: 690000
A23: Pensionsrueckstellungen | B23: Pension provisions | C23: 0 | D23: 0 | E23: 0 | F23: 0 | G23: 0 | H23: 0 | I23: 0
A24: Verb. Kreditinstitute < 1 Jahr | B24: Bank debt, short term | C24: 420000 | D24: 420000 | E24: 1480000 | F24: 380000 | G24: 0 | H24: 90000 | I24: 120000
A25: Verb. Kreditinstitute > 1 Jahr | B25: Bank debt, long term | C25: 1250000 | D25: 1250000 | E25: 320000 | F25: 1180000 | G25: 180000 | H25: 560000 | I25: 1340000
A26: Verbindlichkeiten aus L+L | B26: Trade payables | C26: 680000 | D26: 680000 | E26: 1690000 | F26: 295000 | G26: 340000 | H26: 322000 | I26: 690000
A27: Sonstige Verbindlichkeiten < 1 Jahr | B27: Other liabilities, short term | C27: 240000 | D27: 240000 | E27: 489000 | F27: 377000 | G27: 380000 | H27: 120000 | I27: 190000
... A29: Passive Rechnungsabgrenzung | B29: Deferred income | C29: 0 | D29: 0 | E29: 0 | F29: 0 | G29: 0 | H29: 0 | I29: 0
A30: SONDERPOSITIONEN | B30: The items that decide fixability
A31: Gesellschafterdarlehen | B31: Shareholder loan | C31: 600000 | D31: 600000 | E31: 0 | F31: 0 | G31: 0 | H31: 320000 | I31: 0
A32: Rangruecktritt vorhanden (1 = ja) | B32: Subordination agreement in place | C32: 0 | D32: 0 | E32: 0 | F32: 0 | G32: 0 | H32: 0 | I32: 0
A33: Kontokorrentlinie (Limit) | B33: Overdraft facility limit | C33: 500000 | D33: 500000 | E33: 1500000 | F33: 400000 | G33: 300000 | H33: 250000 | I33: 800000
A34: Kontokorrent-Inanspruchnahme | B34: Overdraft drawn | C34: 420000 | D34: 420000 | E34: 1460000 | F34: 380000 | G34: 0 | H34: 90000 | I34: 0
A35: Leasingverpflichtungen | B35: Off-balance-sheet leasing | C35: 0 | D35: 0 | E35: 0 | F35: 0 | G35: 0 | H35: 0 | I35: 0
A36: GUV (HGB §275, Gesamtkostenverfahren) | B36: Income statement
A37: Periodenlaenge in Monaten | B37: 1-12; a mid-year BWA is annualised | C37: 12 | D37: 12 | E37: 12 | F37: 12 | G37: 12 | H37: 12 | I37: 12
A38: Umsatzerloese | B38: Revenue | C38: 8200000 | D38: 8200000 | E38: 11400000 | F38: 2980000 | G38: 7850000 | H38: 3640000 | I38: 14600000
A39: Bestandsveraenderungen | B39: Change in inventories | C39: 0 | D39: 0 | E39: 0 | F39: 0 | G39: 0 | H39: 0 | I39: 0
A40: Sonstige betriebliche Ertraege | B40: Other operating income | C40: 45000 | D40: 45000 | E40: 0 | F40: 0 | G40: 0 | H40: 0 | I40: 85000
A41: Materialaufwand | B41: Cost of materials | C41: 4180000 | D41: 4180000 | E41: 8950000 | F41: 1090000 | G41: 1180000 | H41: 1580000 | I41: 6100000
A42: Personalaufwand | B42: Personnel expenses | C42: 2650000 | D42: 2650000 | E42: 1420000 | F42: 1520000 | G42: 5100000 | H42: 1480000 | I42: 5180000
A43: Abschreibungen | B43: Depreciation and amortisation | C43: 245000 | D43: 245000 | E43: 95000 | F43: 210000 | G43: 105000 | H43: 92000 | I43: 480000
A44: Sonstige betriebliche Aufwendungen | B44: Other operating expenses | C44: 790000 | D44: 790000 | E44: 640000 | F44: 520000 | G44: 820000 | H44: 330000 | I44: 1580000
A45: Zinsertraege | B45: Interest income | C45: 0 | D45: 0 | E45: 0 | F45: 0 | G45: 0 | H45: 0 | I45: 0
A46: Zinsaufwand | B46: Interest expense | C46: 95000 | D46: 95000 | E46: 148000 | F46: 98000 | G46: 12000 | H46: 34000 | I46: 68000
A47: Steuern | B47: Taxes | C47: 55000 | D47: 55000 | E47: 31000 | F47: 0 | G47: 148000 | H47: 28000 | I47: 310000
A48: VORJAHR (nur fuer Trendaussagen) | B48: Prior year, for growth only
A49: Umsatzerloese Vorjahr | B49: Prior-year revenue (0 = none) | C49: 7650000 | D49: 7650000 | E49: 10900000 | F49: 3780000 | G49: 6420000 | H49: 3480000 | I49: 13900000
A50: Periodenlaenge Vorjahr | B50: Prior-year period months | C50: 12 | D50: 12 | E50: 12 | F50: 12 | G50: 12 | H50: 12 | I50: 12
A51: DARLEHENSDIENST | B51: Debt service from the facility list
A52: Zinsen p.a. (Summe Darlehensliste) | B52: Sum of outstanding x rate | C52: 99900 | D52: 99900 | E52: 146580 | F52: 98940 | G52: 8100 | H52: 32830 | I52: 54940
A53: Tilgung p.a. (Summe Darlehensliste) | B53: Sum of annual principal repayments | C53: 180000 | D53: 180000 | E53: 65000 | F53: 145000 | G53: 60000 | H53: 80000 | I53: 220000
A54: FINANZIERUNGSWUNSCH | B54: The requested new facility
A55: Beantragter Betrag | B55: Requested amount (0 = none) | C55: 750000 | D55: 750000 | E55: 600000 | F55: 350000 | G55: 1200000 | H55: 400000 | I55: 1500000
A56: Laufzeit in Jahren | B56: Tenor in years | C56: 7 | D56: 7 | E56: 5 | F56: 5 | G56: 6 | H56: 8 | I56: 8
A57: Verfuegbare Sicherheiten | B57: Collateral available | C57: 400000 | D57: 400000 | E57: 150000 | F57: 40000 | G57: 180000 | H57: 350000 | I57: 1400000
A58: VERHALTENSDATEN | B58: Behavioural data
A59: Alter der juengsten BWA (Monate) | B59: Age of latest management report | C59: 5 | D59: 5 | E59: 2 | F59: 7 | G59: 2 | H59: 9 | I59: 1
A60: Creditreform Bonitaetsindex (100-600) | B60: Leave empty if no report held | C60: 248 | D60: 248 | E60: 289 | F60: 384 | G60: 195 | H60: 262 | I60: 168
A61: Durchschn. Zahlungsverzug (Tage) | B61: Average days beyond terms | C61: 6 | D61: 6 | E61: 14 | F61: 28 | G61: 2 | H61: 4 | I61: 0
A62: Ruecklastschriften (12 Monate) | B62: Returned direct debits | C62: 0 | D62: 0 | E62: 0 | F62: 3 | G62: 0 | H62: 0 | I62: 0
A63: Tage am KK-Limit (12 Monate) | B63: Days at the overdraft limit | C63: 95 | D63: 95 | E63: 210 | F63: 265 | G63: 0 | H63: 0 | I63: 0
A64: Steuerrueckstaende (1 = ja) | B64: Tax arrears | C64: 0 | D64: 0 | E64: 0 | F64: 1 | G64: 0 | H64: 0 | I64: 0
A65: Planrechnung liegt vor (1 = ja) | B65: Financial plan provided | C65: 0 | D65: 0 | E65: 0 | F65: 0 | G65: 1 | H65: 0 | I65: 1

Sheet Kennzahlen
A1: Zwischengroessen und Kennzahlen / derived figures and ratios
A2: Alles Formeln. Diese Seite ist die eigentliche Nachrechnung von models.py und ratios.py.
A4: Groesse | B4: Formel / formula | C4: Ihr Fall | D4: Mueller Praezisionstechnik GmbH | E4: Nordlicht Handel GmbH & Co. KG | F4: Gastro Rheinblick GmbH | G4: Datenwerk Consulting GmbH | H4: Ihrig Sanitaer- und Heizungstechnik GmbH | I4: Hoffmann Medizintechnik GmbH
A5: ZWISCHENGROESSEN (models.py) | B5: Derived figures
A6: Annualisierungsfaktor | B6: 12 / Periodenmonate | C6: =12/Eingaben!C37 | D6: =12/Eingaben!D37 | E6: =12/Eingaben!E37 | F6: =12/Eingaben!F37 | G6: =12/Eingaben!G37 | H6: =12/Eingaben!H37 | I6: =12/Eingaben!I37
A7: Anlagevermoegen | B7: immat + Sachanlagen + Finanzanlagen | C7: =Eingaben!C6+Eingaben!C7+Eingaben!C8 | D7: =Eingaben!D6+Eingaben!D7+Eingaben!D8 | E7: =Eingaben!E6+Eingaben!E7+Eingaben!E8 | F7: =Eingaben!F6+Eingaben!F7+Eingaben!F8 | G7: =Eingaben!G6+Eingaben!G7+Eingaben!G8 | H7: =Eingaben!H6+Eingaben!H7+Eingaben!H8 | I7: =Eingaben!I6+Eingaben!I7+Eingaben!I8
A8: Umlaufvermoegen | B8: Vorraete + Ford. + sonst. VG + WP + liquide Mittel | C8: =Eingaben!C9+Eingaben!C10+Eingaben!C11+Eingaben!C12+Eingaben!C13 | D8: =Eingaben!D9+Eingaben!D10+Eingaben!D11+Eingaben!D12+Eingaben!D13 | E8: =Eingaben!E9+Eingaben!E10+Eingaben!E11+Eingaben!E12+Eingaben!E13 | F8: =Eingaben!F9+Eingaben!F10+Eingaben!F11+Eingaben!F12+Eingaben!F13 | G8: =Eingaben!G9+Eingaben!G10+Eingaben!G11+Eingaben!G12+Eingaben!G13 | H8: =Eingaben!H9+Eingaben!H10+Eingaben!H11+Eingaben!H12+Eingaben!H13 | I8: =Eingaben!I9+Eingaben!I10+Eingaben!I11+Eingaben!I12+Eingaben!I13
A9: Bilanzsumme (Aktiva) | B9: AV + UV + ARAP | C9: =C7+C8+Eingaben!C14 | D9: =D7+D8+Eingaben!D14 | E9: =E7+E8+Eingaben!E14 | F9: =F7+F8+Eingaben!F14 | G9: =G7+G8+Eingaben!G14 | H9: =H7+H8+Eingaben!H14 | I9: =I7+I8+Eingaben!I14
A10: Summe Passiva (Probe) | B10: EK + Rueckst. + Verb. + PRAP + Ges.darlehen | C10: =C13+Eingaben!C22+Eingaben!C23+Eingaben!C24+Eingaben!C25+Eingaben!C26+Eingaben!C27+Eingaben!C28+Eingaben!C31+Eingaben!C29 | D10: =D13+Eingaben!D22+Eingaben!D23+Eingaben!D24+Eingaben!D25+Eingaben!D26+Eingaben!D27+Eingaben!D28+Eingaben!D31+Eingaben!D29 | E10: =E13+Eingaben!E22+Eingaben!E23+Eingaben!E24+Eingaben!E25+Eingaben!E26+Eingaben!E27+Eingaben!E28+Eingaben!E31+Eingaben!E29 | F10: =F13+Eingaben!F22+Eingaben!F23+Eingaben!F24+Eingaben!F25+Eingaben!F26+Eingaben!F27+Eingaben!F28+Eingaben!F31+Eingaben!F29 | G10: =G13+Eingaben!G22+Eingaben!G23+Eingaben!G24+Eingaben!G25+Eingaben!G26+Eingaben!G27+Eingaben!G28+Eingaben!G31+Eingaben!G29 | H10: =H13+Eingaben!H22+Eingaben!H23+Eingaben!H24+Eingaben!H25+Eingaben!H26+Eingaben!H27+Eingaben!H28+Eingaben!H31+Eingaben!H29 | I10: =I13+Eingaben!I22+Eingaben!I23+Eingaben!I24+Eingaben!I25+Eingaben!I26+Eingaben!I27+Eingaben!I28+Eingaben!I31+Eingaben!I29
A11: Bilanzprobe: Aktiva - Passiva | B11: Muss ~0 sein, sonst blockiert die Engine | C11: =C9-C10 | D11: =D9-D10 | E11: =E9-E10 | F11: =F9-F10 | G11: =G9-G10 | H11: =H9-H10 | I11: =I9-I10
A12: Bilanz ausgeglichen? | B12: Toleranz: max(1 EUR; 0,5% der Bilanzsumme) | C12: =IF(ABS(C11)<=MAX(1,0.005*C9),"OK","FEHLER - Engine bricht ab") | D12: =IF(ABS(D11)<=MAX(1,0.005*D9),"OK","FEHLER - Engine bricht ab") | E12: =IF(ABS(E11)<=MAX(1,0.005*E9),"OK","FEHLER - Engine bricht ab") | F12: =IF(ABS(F11)<=MAX(1,0.005*F9),"OK","FEHLER - Engine bricht ab") | G12: =IF(ABS(G11)<=MAX(1,0.005*G9),"OK","FEHLER - Engine bricht ab") | H12: =IF(ABS(H11)<=MAX(1,0.005*H9),"OK","FEHLER - Engine bricht ab") | I12: =IF(ABS(I11)<=MAX(1,0.005*I9),"OK","FEHLER - Engine bricht ab")
A13: Bilanzielles Eigenkapital | B13: gez. Kapital + Ruecklagen + Vortrag + JUE - ausst. Einlagen | C13: =Eingaben!C16+Eingaben!C17+Eingaben!C18+Eingaben!C19+Eingaben!C20-Eingaben!C21 | D13: =Eingaben!D16+Eingaben!D17+Eingaben!D18+Eingaben!D19+Eingaben!D20-Eingaben!D21 | E13: =Eingaben!E16+Eingaben!E17+Eingaben!E18+Eingaben!E19+Eingaben!E20-Eingaben!E21 | F13: =Eingaben!F16+Eingaben!F17+Eingaben!F18+Eingaben!F19+Eingaben!F20-Eingaben!F21 | G13: =Eingaben!G16+Eingaben!G17+Eingaben!G18+Eingaben!G19+Eingaben!G20-Eingaben!G21 | H13: =Eingaben!H16+Eingaben!H17+Eingaben!H18+Eingaben!H19+Eingaben!H20-Eingaben!H21 | I13: =Eingaben!I16+Eingaben!I17+Eingaben!I18+Eingaben!I19+Eingaben!I20-Eingaben!I21
A14: Wirtschaftliches Eigenkapital | B14: + Gesellschafterdarlehen, wenn Rangruecktritt | C14: =C13+IF(Eingaben!C32=1,Eingaben!C31,0) | D14: =D13+IF(Eingaben!D32=1,Eingaben!D31,0) | E14: =E13+IF(Eingaben!E32=1,Eingaben!E31,0) | F14: =F13+IF(Eingaben!F32=1,Eingaben!F31,0) | G14: =G13+IF(Eingaben!G32=1,Eingaben!G31,0) | H14: =H13+IF(Eingaben!H32=1,Eingaben!H31,0) | I14: =I13+IF(Eingaben!I32=1,Eingaben!I31,0)
A15: Finanzverbindlichkeiten | B15: Bankschulden + Ges.darlehen ohne Rangruecktritt | C15: =Eingaben!C24+Eingaben!C25+IF(Eingaben!C32=1,0,Eingaben!C31) | D15: =Eingaben!D24+Eingaben!D25+IF(Eingaben!D32=1,0,Eingaben!D31) | E15: =Eingaben!E24+Eingaben!E25+IF(Eingaben!E32=1,0,Eingaben!E31) | F15: =Eingaben!F24+Eingaben!F25+IF(Eingaben!F32=1,0,Eingaben!F31) | G15: =Eingaben!G24+Eingaben!G25+IF(Eingaben!G32=1,0,Eingaben!G31) | H15: =Eingaben!H24+Eingaben!H25+IF(Eingaben!H32=1,0,Eingaben!H31) | I15: =Eingaben!I24+Eingaben!I25+IF(Eingaben!I32=1,0,Eingaben!I31)
A16: Nettofinanzverbindlichkeiten | B16: abzgl. liquide Mittel und Wertpapiere, min. 0 | C16: =MAX(0,C15-Eingaben!C13-Eingaben!C12) | D16: =MAX(0,D15-Eingaben!D13-Eingaben!D12) | E16: =MAX(0,E15-Eingaben!E13-Eingaben!E12) | F16: =MAX(0,F15-Eingaben!F13-Eingaben!F12) | G16: =MAX(0,G15-Eingaben!G13-Eingaben!G12) | H16: =MAX(0,H15-Eingaben!H13-Eingaben!H12) | I16: =MAX(0,I15-Eingaben!I13-Eingaben!I12)
A17: Kurzfristige Verbindlichkeiten | B17: Bank kurz + L+L + sonstige kurz | C17: =Eingaben!C24+Eingaben!C26+Eingaben!C27 | D17: =Eingaben!D24+Eingaben!D26+Eingaben!D27 | E17: =Eingaben!E24+Eingaben!E26+Eingaben!E27 | F17: =Eingaben!F24+Eingaben!F26+Eingaben!F27 | G17: =Eingaben!G24+Eingaben!G26+Eingaben!G27 | H17: =Eingaben!H24+Eingaben!H26+Eingaben!H27 | I17: =Eingaben!I24+Eingaben!I26+Eingaben!I27
A18: Langfristiges Kapital | B18: wirtsch. EK + Bank lang + sonst. lang + Pensionen | C18: =C14+Eingaben!C25+Eingaben!C28+Eingaben!C23 | D18: =D14+Eingaben!D25+Eingaben!D28+Eingaben!D23 | E18: =E14+Eingaben!E25+Eingaben!E28+Eingaben!E23 | F18: =F14+Eingaben!F25+Eingaben!F28+Eingaben!F23 | G18: =G14+Eingaben!G25+Eingaben!G28+Eingaben!G23 | H18: =H14+Eingaben!H25+Eingaben!H28+Eingaben!H23 | I18: =I14+Eingaben!I25+Eingaben!I28+Eingaben!I23
A19: ANNUALISIERTE GUV-GROESSEN (ratios.py) | B19: Flows, annualised
A20: Gesamtleistung | B20: Umsatz + Bestandsveraenderung + sonst. Ertraege | C20: =(Eingaben!C38+Eingaben!C39+Eingaben!C40)*C6 | D20: =(Eingaben!D38+Eingaben!D39+Eingaben!D40)*D6 | E20: =(Eingaben!E38+Eingaben!E39+Eingaben!E40)*E6 | F20: =(Eingaben!F38+Eingaben!F39+Eingaben!F40)*F6 | G20: =(Eingaben!G38+Eingaben!G39+Eingaben!G40)*G6 | H20: =(Eingaben!H38+Eingaben!H39+Eingaben!H40)*H6 | I20: =(Eingaben!I38+Eingaben!I39+Eingaben!I40)*I6
A21: Umsatz (annualisiert) | C21: =Eingaben!C38*C6 | D21: =Eingaben!D38*D6 | E21: =Eingaben!E38*E6 | F21: =Eingaben!F38*F6 | G21: =Eingaben!G38*G6 | H21: =Eingaben!H38*H6 | I21: =Eingaben!I38*I6
A22: EBITDA (annualisiert) | B22: Gesamtleistung - Material - Personal - sonst. Aufwand | C22: =C20-(Eingaben!C41+Eingaben!C42+Eingaben!C44)*C6 | D22: =D20-(Eingaben!D41+Eingaben!D42+Eingaben!D44)*D6 | E22: =E20-(Eingaben!E41+Eingaben!E42+Eingaben!E44)*E6 | F22: =F20-(Eingaben!F41+Eingaben!F42+Eingaben!F44)*F6 | G22: =G20-(Eingaben!G41+Eingaben!G42+Eingaben!G44)*G6 | H22: =H20-(Eingaben!H41+Eingaben!H42+Eingaben!H44)*H6 | I22: =I20-(Eingaben!I41+Eingaben!I42+Eingaben!I44)*I6
A23: EBIT (annualisiert) | B23: EBITDA - Abschreibungen | C23: =C22-Eingaben!C43*C6 | D23: =D22-Eingaben!D43*D6 | E23: =E22-Eingaben!E43*E6 | F23: =F22-Eingaben!F43*F6 | G23: =G22-Eingaben!G43*G6 | H23: =H22-Eingaben!H43*H6 | I23: =I22-Eingaben!I43*I6
A24: Zinsaufwand (annualisiert) | C24: =Eingaben!C46*C6 | D24: =Eingaben!D46*D6 | E24: =Eingaben!E46*E6 | F24: =Eingaben!F46*F6 | G24: =Eingaben!G46*G6 | H24: =Eingaben!H46*H6 | I24: =Eingaben!I46*I6
A25: Materialaufwand (annualisiert) | C25: =Eingaben!C41*C6 | D25: =Eingaben!D41*D6 | E25: =Eingaben!E41*E6 | F25: =Eingaben!F41*F6 | G25: =Eingaben!G41*G6 | H25: =Eingaben!H41*H6 | I25: =Eingaben!I41*I6
A26: Jahresueberschuss laut GuV | B26: EBIT + Zinsertrag - Zinsaufwand - Steuern (nicht annualisiert) | C26: =(C23/C6)+Eingaben!C45-Eingaben!C46-Eingaben!C47 | D26: =(D23/D6)+Eingaben!D45-Eingaben!D46-Eingaben!D47 | E26: =(E23/E6)+Eingaben!E45-Eingaben!E46-Eingaben!E47 | F26: =(F23/F6)+Eingaben!F45-Eingaben!F46-Eingaben!F47 | G26: =(G23/G6)+Eingaben!G45-Eingaben!G46-Eingaben!G47 | H26: =(H23/H6)+Eingaben!H45-Eingaben!H46-Eingaben!H47 | I26: =(I23/I6)+Eingaben!I45-Eingaben!I46-Eingaben!I47
A27: Ergebnis GuV = Ergebnis Bilanz? | B27: Nur bei 12-Monats-Periode geprueft | C27: =IF(Eingaben!C37<>12,"n/a (Rumpfperiode)",IF(ABS(C26-Eingaben!C20)<=MAX(1,0.002*C9),"OK","FEHLER - Engine bricht ab")) | D27: =IF(Eingaben!D37<>12,"n/a (Rumpfperiode)",IF(ABS(D26-Eingaben!D20)<=MAX(1,0.002*D9),"OK","FEHLER - Engine bricht ab")) | E27: =IF(Eingaben!E37<>12,"n/a (Rumpfperiode)",IF(ABS(E26-Eingaben!E20)<=MAX(1,0.002*E9),"OK","FEHLER - Engine bricht ab")) | F27: =IF(Eingaben!F37<>12,"n/a (Rumpfperiode)",IF(ABS(F26-Eingaben!F20)<=MAX(1,0.002*F9),"OK","FEHLER - Engine bricht ab")) | G27: =IF(Eingaben!G37<>12,"n/a (Rumpfperiode)",IF(ABS(G26-Eingaben!G20)<=MAX(1,0.002*G9),"OK","FEHLER - Engine bricht ab")) | H27: =IF(Eingaben!H37<>12,"n/a (Rumpfperiode)",IF(ABS(H26-Eingaben!H20)<=MAX(1,0.002*H9),"OK","FEHLER - Engine bricht ab")) | I27: =IF(Eingaben!I37<>12,"n/a (Rumpfperiode)",IF(ABS(I26-Eingaben!I20)<=MAX(1,0.002*I9),"OK","FEHLER - Engine bricht ab"))
A28: KAPITALDIENST | B28: Debt service
A29: Kapitaldienst (bestehend) | B29: Zinsen + Tilgung aus der Darlehensliste | C29: =Eingaben!C52+Eingaben!C53 | D29: =Eingaben!D52+Eingaben!D53 | E29: =Eingaben!E52+Eingaben!E53 | F29: =Eingaben!F52+Eingaben!F53 | G29: =Eingaben!G52+Eingaben!G53 | H29: =Eingaben!H52+Eingaben!H53 | I29: =Eingaben!I52+Eingaben!I53
A30: Annuitaet der neuen Finanzierung | B30: 6,5% p.a., Laufzeit wie beantragt (konservativ) | C30: =IF(Eingaben!C55<=0,0,Eingaben!C55*(0.065*(1+0.065)^MAX(1,Eingaben!C56))/((1+0.065)^MAX(1,Eingaben!C56)-1)) | D30: =IF(Eingaben!D55<=0,0,Eingaben!D55*(0.065*(1+0.065)^MAX(1,Eingaben!D56))/((1+0.065)^MAX(1,Eingaben!D56)-1)) | E30: =IF(Eingaben!E55<=0,0,Eingaben!E55*(0.065*(1+0.065)^MAX(1,Eingaben!E56))/((1+0.065)^MAX(1,Eingaben!E56)-1)) | F30: =IF(Eingaben!F55<=0,0,Eingaben!F55*(0.065*(1+0.065)^MAX(1,Eingaben!F56))/((1+0.065)^MAX(1,Eingaben!F56)-1)) | G30: =IF(Eingaben!G55<=0,0,Eingaben!G55*(0.065*(1+0.065)^MAX(1,Eingaben!G56))/((1+0.065)^MAX(1,Eingaben!G56)-1)) | H30: =IF(Eingaben!H55<=0,0,Eingaben!H55*(0.065*(1+0.065)^MAX(1,Eingaben!H56))/((1+0.065)^MAX(1,Eingaben!H56)-1)) | I30: =IF(Eingaben!I55<=0,0,Eingaben!I55*(0.065*(1+0.065)^MAX(1,Eingaben!I56))/((1+0.065)^MAX(1,Eingaben!I56)-1))
A31: Kapitaldienst inkl. neuer Finanzierung | C31: =C29+C30 | D31: =D29+D30 | E31: =E29+E30 | F31: =F29+F30 | G31: =G29+G30 | H31: =H29+H30 | I31: =I29+I30
A32: KENNZAHLEN (ratios.py) | B32: Ratios
A33: Eigenkapitalquote (wirtschaftlich) | B33: wirtsch. EK / Bilanzsumme -- Faktor 1 | C33: =IF(C9=0,"",C14/C9) | D33: =IF(D9=0,"",D14/D9) | E33: =IF(E9=0,"",E14/E9) | F33: =IF(F9=0,"",F14/F9) | G33: =IF(G9=0,"",G14/G9) | H33: =IF(H9=0,"",H14/H9) | I33: =IF(I9=0,"",I14/I9)
A34: Eigenkapitalquote (bilanziell) | B34: nachrichtlich | C34: =IF(C9=0,"",C13/C9) | D34: =IF(D9=0,"",D13/D9) | E34: =IF(E9=0,"",E13/E9) | F34: =IF(F9=0,"",F13/F9) | G34: =IF(G9=0,"",G13/G9) | H34: =IF(H9=0,"",H13/H9) | I34: =IF(I9=0,"",I13/I9)
A35: Anlagendeckungsgrad II | B35: langfr. Kapital / Anlagevermoegen -- Regel R06 | C35: =IF(C7=0,"",C18/C7) | D35: =IF(D7=0,"",D18/D7) | E35: =IF(E7=0,"",E18/E7) | F35: =IF(F7=0,"",F18/F7) | G35: =IF(G7=0,"",G18/G7) | H35: =IF(H7=0,"",H18/H7) | I35: =IF(I7=0,"",I18/I7)
A36: Dynamischer Verschuldungsgrad | B36: Nettoverschuldung / EBITDA -- Faktor 3 | C36: =IF(C22<=0,"",C16/C22) | D36: =IF(D22<=0,"",D16/D22) | E36: =IF(E22<=0,"",E16/E22) | F36: =IF(F22<=0,"",F16/F22) | G36: =IF(G22<=0,"",G16/G22) | H36: =IF(H22<=0,"",H16/H22) | I36: =IF(I22<=0,"",I16/I22)
A37: Kapitaldienstfaehigkeit (bestehend) | B37: EBITDA / Kapitaldienst | C37: =IF(C29<=0,"",C22/C29) | D37: =IF(D29<=0,"",D22/D29) | E37: =IF(E29<=0,"",E22/E29) | F37: =IF(F29<=0,"",F22/F29) | G37: =IF(G29<=0,"",G22/G29) | H37: =IF(H29<=0,"",H22/H29) | I37: =IF(I29<=0,"",I22/I29)
A38: Kapitaldienstfaehigkeit inkl. neu | B38: EBITDA / Kapitaldienst inkl. neu -- Faktor 2 | C38: =IF(C31<=0,"",C22/C31) | D38: =IF(D31<=0,"",D22/D31) | E38: =IF(E31<=0,"",E22/E31) | F38: =IF(F31<=0,"",F22/F31) | G38: =IF(G31<=0,"",G22/G31) | H38: =IF(H31<=0,"",H22/H31) | I38: =IF(I31<=0,"",I22/I31)
A39: Zinsdeckungsgrad | B39: EBIT / Zinsaufwand -- Faktor 6 | C39: =IF(C24=0,"",C23/C24) | D39: =IF(D24=0,"",D23/D24) | E39: =IF(E24=0,"",E23/E24) | F39: =IF(F24=0,"",F23/F24) | G39: =IF(G24=0,"",G23/G24) | H39: =IF(H24=0,"",H23/H24) | I39: =IF(I24=0,"",I23/I24)
A40: EBITDA-Marge | B40: nachrichtlich | C40: =IF(C21=0,"",C22/C21) | D40: =IF(D21=0,"",D22/D21) | E40: =IF(E21=0,"",E22/E21) | F40: =IF(F21=0,"",F22/F21) | G40: =IF(G21=0,"",G22/G21) | H40: =IF(H21=0,"",H22/H21) | I40: =IF(I21=0,"",I22/I21)
A41: EBIT-Marge | B41: EBIT / Umsatz -- Faktor 4 | C41: =IF(C21=0,"",C23/C21) | D41: =IF(D21=0,"",D23/D21) | E41: =IF(E21=0,"",E23/E21) | F41: =IF(F21=0,"",F23/F21) | G41: =IF(G21=0,"",G23/G21) | H41: =IF(H21=0,"",H23/H21) | I41: =IF(I21=0,"",I23/I21)
A42: Gesamtkapitalrentabilitaet | B42: EBIT / Bilanzsumme | C42: =IF(C9=0,"",C23/C9) | D42: =IF(D9=0,"",D23/D9) | E42: =IF(E9=0,"",E23/E9) | F42: =IF(F9=0,"",F23/F9) | G42: =IF(G9=0,"",G23/G9) | H42: =IF(H9=0,"",H23/H9) | I42: =IF(I9=0,"",I23/I9)
A43: Umsatzwachstum | B43: gegen Vorjahr, annualisiert -- Regel R08 | C43: =IF(Eingaben!C49<=0,"",(C21-Eingaben!C49*12/Eingaben!C50)/(Eingaben!C49*12/Eingaben!C50)) | D43: =IF(Eingaben!D49<=0,"",(D21-Eingaben!D49*12/Eingaben!D50)/(Eingaben!D49*12/Eingaben!D50)) | E43: =IF(Eingaben!E49<=0,"",(E21-Eingaben!E49*12/Eingaben!E50)/(Eingaben!E49*12/Eingaben!E50)) | F43: =IF(Eingaben!F49<=0,"",(F21-Eingaben!F49*12/Eingaben!F50)/(Eingaben!F49*12/Eingaben!F50)) | G43: =IF(Eingaben!G49<=0,"",(G21-Eingaben!G49*12/Eingaben!G50)/(Eingaben!G49*12/Eingaben!G50)) | H43: =IF(Eingaben!H49<=0,"",(H21-Eingaben!H49*12/Eingaben!H50)/(Eingaben!H49*12/Eingaben!H50)) | I43: =IF(Eingaben!I49<=0,"",(I21-Eingaben!I49*12/Eingaben!I50)/(Eingaben!I49*12/Eingaben!I50))
A44: Liquiditaet 2. Grades | B44: (Forderungen + liquide Mittel + WP) / kurzfr. Verb. -- Faktor 5 | C44: =IF(C17=0,"",(Eingaben!C10+Eingaben!C13+Eingaben!C12)/C17) | D44: =IF(D17=0,"",(Eingaben!D10+Eingaben!D13+Eingaben!D12)/D17) | E44: =IF(E17=0,"",(Eingaben!E10+Eingaben!E13+Eingaben!E12)/E17) | F44: =IF(F17=0,"",(Eingaben!F10+Eingaben!F13+Eingaben!F12)/F17) | G44: =IF(G17=0,"",(Eingaben!G10+Eingaben!G13+Eingaben!G12)/G17) | H44: =IF(H17=0,"",(Eingaben!H10+Eingaben!H13+Eingaben!H12)/H17) | I44: =IF(I17=0,"",(Eingaben!I10+Eingaben!I13+Eingaben!I12)/I17)
A45: Liquiditaet 3. Grades | B45: Umlaufvermoegen / kurzfr. Verbindlichkeiten | C45: =IF(C17=0,"",C8/C17) | D45: =IF(D17=0,"",D8/D17) | E45: =IF(E17=0,"",E8/E17) | F45: =IF(F17=0,"",F8/F17) | G45: =IF(G17=0,"",G8/G17) | H45: =IF(H17=0,"",H8/H17) | I45: =IF(I17=0,"",I8/I17)
A46: Working Capital | B46: UV - kurzfristige Verbindlichkeiten | C46: =C8-C17 | D46: =D8-D17 | E46: =E8-E17 | F46: =F8-F17 | G46: =G8-G17 | H46: =H8-H17 | I46: =I8-I17
A47: Debitorenlaufzeit (Tage) | B47: Forderungen / Umsatz x 365 -- Regel R05 | C47: =IF(C21<=0,"",Eingaben!C10/C21*365) | D47: =IF(D21<=0,"",Eingaben!D10/D21*365) | E47: =IF(E21<=0,"",Eingaben!E10/E21*365) | F47: =IF(F21<=0,"",Eingaben!F10/F21*365) | G47: =IF(G21<=0,"",Eingaben!G10/G21*365) | H47: =IF(H21<=0,"",Eingaben!H10/H21*365) | I47: =IF(I21<=0,"",Eingaben!I10/I21*365)
A48: Kreditorenlaufzeit (Tage) | B48: Verb. L+L / Materialaufwand x 365 | C48: =IF(C25<=0,"",Eingaben!C26/C25*365) | D48: =IF(D25<=0,"",Eingaben!D26/D25*365) | E48: =IF(E25<=0,"",Eingaben!E26/E25*365) | F48: =IF(F25<=0,"",Eingaben!F26/F25*365) | G48: =IF(G25<=0,"",Eingaben!G26/G25*365) | H48: =IF(H25<=0,"",Eingaben!H26/H25*365) | I48: =IF(I25<=0,"",Eingaben!I26/I25*365)
A49: Vorratsreichweite (Tage) | B49: Vorraete / Materialaufwand x 365 -- Regel R10 | C49: =IF(C25<=0,"",Eingaben!C9/C25*365) | D49: =IF(D25<=0,"",Eingaben!D9/D25*365) | E49: =IF(E25<=0,"",Eingaben!E9/E25*365) | F49: =IF(F25<=0,"",Eingaben!F9/F25*365) | G49: =IF(G25<=0,"",Eingaben!G9/G25*365) | H49: =IF(H25<=0,"",Eingaben!H9/H25*365) | I49: =IF(I25<=0,"",Eingaben!I9/I25*365)
A50: Cash Conversion Cycle (Tage) | B50: DSO + Vorratsreichweite - DPO | C50: =IF(OR(NOT(ISNUMBER(C47)),NOT(ISNUMBER(C48))),"",C47+C49-C48) | D50: =IF(OR(NOT(ISNUMBER(D47)),NOT(ISNUMBER(D48))),"",D47+D49-D48) | E50: =IF(OR(NOT(ISNUMBER(E47)),NOT(ISNUMBER(E48))),"",E47+E49-E48) | F50: =IF(OR(NOT(ISNUMBER(F47)),NOT(ISNUMBER(F48))),"",F47+F49-F48) | G50: =IF(OR(NOT(ISNUMBER(G47)),NOT(ISNUMBER(G48))),"",G47+G49-G48) | H50: =IF(OR(NOT(ISNUMBER(H47)),NOT(ISNUMBER(H48))),"",H47+H49-H48) | I50: =IF(OR(NOT(ISNUMBER(I47)),NOT(ISNUMBER(I48))),"",I47+I49-I48)
A51: Kontokorrent-Auslastung | B51: Inanspruchnahme / Limit -- Faktor 7 | C51: =IF(Eingaben!C33<=0,"",Eingaben!C34/Eingaben!C33) | D51: =IF(Eingaben!D33<=0,"",Eingaben!D34/Eingaben!D33) | E51: =IF(Eingaben!E33<=0,"",Eingaben!E34/Eingaben!E33) | F51: =IF(Eingaben!F33<=0,"",Eingaben!F34/Eingaben!F33) | G51: =IF(Eingaben!G33<=0,"",Eingaben!G34/Eingaben!G33) | H51: =IF(Eingaben!H33<=0,"",Eingaben!H34/Eingaben!H33) | I51: =IF(Eingaben!I33<=0,"",Eingaben!I34/Eingaben!I33)
A52: Zahlungsverhalten-Index (0-100) | B52: 100 - Verzug x2,5 (max 45) - Ruecklast. x12 (max 30) - Steuer 30 - KK-Tage | C52: =MAX(0,100-MIN(45,Eingaben!C61*2.5)-MIN(30,Eingaben!C62*12)-IF(Eingaben!C64=1,30,0)-IF(Eingaben!C63>60,15,IF(Eingaben!C63>20,7,0))) | D52: =MAX(0,100-MIN(45,Eingaben!D61*2.5)-MIN(30,Eingaben!D62*12)-IF(Eingaben!D64=1,30,0)-IF(Eingaben!D63>60,15,IF(Eingaben!D63>20,7,0))) | E52: =MAX(0,100-MIN(45,Eingaben!E61*2.5)-MIN(30,Eingaben!E62*12)-IF(Eingaben!E64=1,30,0)-IF(Eingaben!E63>60,15,IF(Eingaben!E63>20,7,0))) | F52: =MAX(0,100-MIN(45,Eingaben!F61*2.5)-MIN(30,Eingaben!F62*12)-IF(Eingaben!F64=1,30,0)-IF(Eingaben!F63>60,15,IF(Eingaben!F63>20,7,0))) | G52: =MAX(0,100-MIN(45,Eingaben!G61*2.5)-MIN(30,Eingaben!G62*12)-IF(Eingaben!G64=1,30,0)-IF(Eingaben!G63>60,15,IF(Eingaben!G63>20,7,0))) | H52: =MAX(0,100-MIN(45,Eingaben!H61*2.5)-MIN(30,Eingaben!H62*12)-IF(Eingaben!H64=1,30,0)-IF(Eingaben!H63>60,15,IF(Eingaben!H63>20,7,0))) | I52: =MAX(0,100-MIN(45,Eingaben!I61*2.5)-MIN(30,Eingaben!I62*12)-IF(Eingaben!I64=1,30,0)-IF(Eingaben!I63>60,15,IF(Eingaben!I63>20,7,0)))

Sheet Scorecard
A1: Scorecard / scoring
A2: Je Fall zwei Spalten: der Rohwert und die daraus interpolierten Punkte (0-100).
A4: Faktor | B4: Gewicht | C4: Einheit | D4: Ihr Fall | E4: Punkte | F4: Beitrag | G4: Mueller Praezisionstechnik GmbH | H4: Punkte | I4: Beitrag | J4: Nordlicht Handel GmbH & Co. KG | K4: Punkte | L4: Beitrag | M4: Gastro Rheinblick GmbH | N4: Punkte | O4: Beitrag | P4: Datenwerk Consulting GmbH | Q4: Punkte | R4: Beitrag | S4: Ihrig Sanitaer- und Heizungstechnik GmbH | T4: Punkte | U4: Beitrag | V4: Hoffmann Medizintechnik GmbH | W4: Punkte | X4: Beitrag
A5: Eigenkapitalquote (wirtschaftlich) | B5: 0.2 | C5: percent | D5: =IF(Kennzahlen!C33="","",Kennzahlen!C33) | E5: =IF(NOT(ISNUMBER(D5)),"",IF(D5<=INDEX(bpx_eigenkapitalquote,1),INDEX(bpy_eigenkapitalquote,1),IF(D5>=INDEX(bpx_eigenkapitalquote,COUNT(bpx_eigenkapitalquote)),INDEX(bpy_eigenkapitalquote,COUNT(bpx_eigenkapitalquote)),INDEX(bpy_eigenkapitalquote,MATCH(D5,bpx_eigenkapitalquote,1))+(D5-INDEX(bpx_eigenkapitalquote,MATCH(D5,bpx_eigenkapitalquote,1)))/(INDEX(bpx_eigenkapitalquote,MATCH(D5,bpx_eigenkapitalquote,1)+1)-INDEX(bpx_eigenkapitalquote,MATCH(D5,bpx_eigenkapitalquote,1)))*(INDEX(bpy_eigenkapitalquote,MATCH(D5,bpx_eigenkapitalquote,1)+1)-INDEX(bpy_eigenkapitalquote,MATCH(D5,bpx_eigenkapitalquote,1)))))) | F5: =IF(ISNUMBER(E5),$B5*E5,0) | G5: =IF(Kennzahlen!D33="","",Kennzahlen!D33) | H5: =IF(NOT(ISNUMBER(G5)),"",IF(G5<=INDEX(bpx_eigenkapitalquote,1),INDEX(bpy_eigenkapitalquote,1),IF(G5>=INDEX(bpx_eigenkapitalquote,COUNT(bpx_eigenkapitalquote)),INDEX(bpy_eigenkapitalquote,COUNT(bpx_eigenkapitalquote)),INDEX(bpy_eigenkapitalquote,MATCH(G5,bpx_eigenkapitalquote,1))+(G5-INDEX(bpx_eigenkapitalquote,MATCH(G5,bpx_eigenkapitalquote,1)))/(INDEX(bpx_eigenkapitalquote,MATCH(G5,bpx_eigenkapitalquote,1)+1)-INDEX(bpx_eigenkapitalquote,MATCH(G5,bpx_eigenkapitalquote,1)))*(INDEX(bpy_eigenkapitalquote,MATCH(G5,bpx_eigenkapitalquote,1)+1)-INDEX(bpy_eigenkapitalquote,MATCH(G5,bpx_eigenkapitalquote,1)))))) | I5: =IF(ISNUMBER(H5),$B5*H5,0) | J5: =IF(Kennzahlen!E33="","",Kennzahlen!E33) | K5: =IF(NOT(ISNUMBER(J5)),"",IF(J5<=INDEX(bpx_eigenkapitalquote,1),INDEX(bpy_eigenkapitalquote,1),IF(J5>=INDEX(bpx_eigenkapitalquote,COUNT(bpx_eigenkapitalquote)),INDEX(bpy_eigenkapitalquote,COUNT(bpx_eigenkapitalquote)),INDEX(bpy_eigenkapitalquote,MATCH(J5,bpx_eigenkapitalquote,1))+(J5-INDEX(bpx_eigenkapitalquote,MATCH(J5,bpx_eigenkapitalquote,1)))/(INDEX(bpx_eigenkapitalquote,MATCH(J5,bpx_eigenkapitalquote,1)+1)-INDEX(bpx_eigenkapitalquote,MATCH(J5,bpx_eigenkapitalquote,1)))*(INDEX(bpy_eigenkapitalquote,MATCH(J5,bpx_eigenkapitalquote,1)+1)-INDEX(bpy_eigenkapitalquote,MATCH(J5,bpx_eigenkapitalquote,1)))))) | L5: =IF(ISNUMBER(K5),$B5*K5,0) | M5: =IF(Kennzahlen!F33="","",Kennzahlen!F33) | N5: =IF(NOT(ISNUMBER(M5)),"",IF(M5<=INDEX(bpx_eigenkapitalquote,1),INDEX(bpy_eigenkapitalquote,1),IF(M5>=INDEX(bpx_eigenkapitalquote,COUNT(bpx_eigenkapitalquote)),INDEX(bpy_eigenkapitalquote,COUNT(bpx_eigenkapitalquote)),INDEX(bpy_eigenkapitalquote,MATCH(M5,bpx_eigenkapitalquote,1))+(M5-INDEX(bpx_eigenkapitalquote,MATCH(M5,bpx_eigenkapitalquote,1)))/(INDEX(bpx_eigenkapitalquote,MATCH(M5,bpx_eigenkapitalquote,1)+1)-INDEX(bpx_eigenkapitalquote,MATCH(M5,bpx_eigenkapitalquote,1)))*(INDEX(bpy_eigenkapitalquote,MATCH(M5,bpx_eigenkapitalquote,1)+1)-INDEX(bpy_eigenkapitalquote,MATCH(M5,bpx_eigenkapitalquote,1)))))) | O5: =IF(ISNUMBER(N5),$B5*N5,0) | P5: =IF(Kennzahlen!G33="","",Kennzahlen!G33) | Q5: =IF(NOT(ISNUMBER(P5)),"",IF(P5<=INDEX(bpx_eigenkapitalquote,1),INDEX(bpy_eigenkapitalquote,1),IF(P5>=INDEX(bpx_eigenkapitalquote,COUNT(bpx_eigenkapitalquote)),INDEX(bpy_eigenkapitalquote,COUNT(bpx_eigenkapitalquote)),INDEX(bpy_eigenkapitalquote,MATCH(P5,bpx_eigenkapitalquote,1))+(P5-INDEX(bpx_eigenkapitalquote,MATCH(P5,bpx_eigenkapitalquote,1)))/(INDEX(bpx_eigenkapitalquote,MATCH(P5,bpx_eigenkapitalquote,1)+1)-INDEX(bpx_eigenkapitalquote,MATCH(P5,bpx_eigenkapitalquote,1)))*(INDEX(bpy_eigenkapitalquote,MATCH(P5,bpx_eigenkapitalquote,1)+1)-INDEX(bpy_eigenkapitalquote,MATCH(P5,bpx_eigenkapitalquote,1)))))) | R5: =IF(ISNUMBER(Q5),$B5*Q5,0) | S5: =IF(Kennzahlen!H33="","",Kennzahlen!H33) | T5: =IF(NOT(ISNUMBER(S5)),"",IF(S5<=INDEX(bpx_eigenkapitalquote,1),INDEX(bpy_eigenkapitalquote,1),IF(S5>=INDEX(bpx_eigenkapitalquote,COUNT(bpx_eigenkapitalquote)),INDEX(bpy_eigenkapitalquote,COUNT(bpx_eigenkapitalquote)),INDEX(bpy_eigenkapitalquote,MATCH(S5,bpx_eigenkapitalquote,1))+(S5-INDEX(bpx_eigenkapitalquote,MATCH(S5,bpx_eigenkapitalquote,1)))/(INDEX(bpx_eigenkapitalquote,MATCH(S5,bpx_eigenkapitalquote,1)+1)-INDEX(bpx_eigenkapitalquote,MATCH(S5,bpx_eigenkapitalquote,1)))*(INDEX(bpy_eigenkapitalquote,MATCH(S5,bpx_eigenkapitalquote,1)+1)-INDEX(bpy_eigenkapitalquote,MATCH(S5,bpx_eigenkapitalquote,1)))))) | U5: =IF(ISNUMBER(T5),$B5*T5,0) | V5: =IF(Kennzahlen!I33="","",Kennzahlen!I33) | W5: =IF(NOT(ISNUMBER(V5)),"",IF(V5<=INDEX(bpx_eigenkapitalquote,1),INDEX(bpy_eigenkapitalquote,1),IF(V5>=INDEX(bpx_eigenkapitalquote,COUNT(bpx_eigenkapitalquote)),INDEX(bpy_eigenkapitalquote,COUNT(bpx_eigenkapitalquote)),INDEX(bpy_eigenkapitalquote,MATCH(V5,bpx_eigenkapitalquote,1))+(V5-INDEX(bpx_eigenkapitalquote,MATCH(V5,bpx_eigenkapitalquote,1)))/(INDEX(bpx_eigenkapitalquote,MATCH(V5,bpx_eigenkapitalquote,1)+1)-INDEX(bpx_eigenkapitalquote,MATCH(V5,bpx_eigenkapitalquote,1)))*(INDEX(bpy_eigenkapitalquote,MATCH(V5,bpx_eigenkapitalquote,1)+1)-INDEX(bpy_eigenkapitalquote,MATCH(V5,bpx_eigenkapitalquote,1)))))) | X5: =IF(ISNUMBER(W5),$B5*W5,0)
A6: Kapitaldienstfaehigkeit inkl. neuer Finanzierung (DSCR) | B6: 0.2 | C6: x | D6: =IF(Kennzahlen!C38="","",Kennzahlen!C38) | E6: =IF(NOT(ISNUMBER(D6)),"",IF(D6<=INDEX(bpx_kapitaldienstfaehigkeit_inkl_neu,1),INDEX(bpy_kapitaldienstfaehigkeit_inkl_neu,1),IF(D6>=INDEX(bpx_kapitaldienstfaehigkeit_inkl_neu,COUNT(bpx_kapitaldienstfaehigkeit_inkl_neu)),INDEX(bpy_kapitaldienstfaehigkeit_inkl_neu,COUNT(bpx_kapitaldienstfaehigkeit_inkl_neu)),INDEX(bpy_kapitaldienstfaehigkeit_inkl_neu,MATCH(D6,bpx_kapitaldienstfaehigkeit_inkl_neu,1))+(D6-INDEX(bpx_kapitaldienstfaehigkeit_inkl_neu,MATCH(D6,bpx_kapitaldienstfaehigkeit_inkl_neu,1)))/(INDEX(bpx_kapitaldienstfaehigkeit_inkl_neu,MATCH(D6,bpx_kapitaldienstfaehigkeit_inkl_neu,1)+1)-INDEX(bpx_kapitaldienstfaehigkeit_inkl_neu,MATCH(D6,bpx_kapitaldienstfaehigkeit_inkl_neu,1)))*(INDEX(bpy_kapitaldienstfaehigkeit_inkl_neu,MATCH(D6,bpx_kapitaldienstfaehigkeit_inkl_neu,1)+1)-INDEX(bpy_kapitaldienstfaehigkeit_inkl_neu,MATCH(D6,bpx_kapitaldienstfaehigkeit_inkl_neu,1)))))) | F6: =IF(ISNUMBER(E6),$B6*E6,0) | G6: =IF(Kennzahlen!D38="","",Kennzahlen!D38) | H6: =IF(NOT(ISNUMBER(G6)),"",IF(G6<=INDEX(bpx_kapitaldienstfaehigkeit_inkl_neu,1),INDEX(bpy_kapitaldienstfaehigkeit_inkl_neu,1),IF(G6>=INDEX(bpx_kapitaldienstfaehigkeit_inkl_neu,COUNT(bpx_kapitaldienstfaehigkeit_inkl_neu)),INDEX(bpy_kapitaldienstfaehigkeit_inkl_neu,COUNT(bpx_kapitaldienstfaehigkeit_inkl_neu)),INDEX(bpy_kapitaldienstfaehigkeit_inkl_neu,MATCH(G6,bpx_kapitaldienstfaehigkeit_inkl_neu,1))+(G6-INDEX(bpx_kapitaldienstfaehigkeit_inkl_neu,MATCH(G6,bpx_kapitaldienstfaehigkeit_inkl_neu,1)))/(INDEX(bpx_kapitaldienstfaehigkeit_inkl_neu,MATCH(G6,bpx_kapitaldienstfaehigkeit_inkl_neu,1)+1)-INDEX(bpx_kapitaldienstfaehigkeit_inkl_neu,MATCH(G6,bpx_kapitaldienstfaehigkeit_inkl_neu,1)))*(INDEX(bpy_kapitaldienstfaehigkeit_inkl_neu,MATCH(G6,bpx_kapitaldienstfaehigkeit_inkl_neu,1)+1)-INDEX(bpy_kapitaldienstfaehigkeit_inkl_neu,MATCH(G6,bpx_kapitaldienstfaehigkeit_inkl_neu,1)))))) | I6: =IF(ISNUMBER(H6),$B6*H6,0) | J6: =IF(Kennzahlen!E38="","",Kennzahlen!E38) | K6: =IF(NOT(ISNUMBER(J6)),"",IF(J6<=INDEX(bpx_kapitaldienstfaehigkeit_inkl_neu,1),INDEX(bpy_kapitaldienstfaehigkeit_inkl_neu,1),IF(J6>=INDEX(bpx_kapitaldienstfaehigkeit_inkl_neu,COUNT(bpx_kapitaldienstfaehigkeit_inkl_neu)),INDEX(bpy_kapitaldienstfaehigkeit_inkl_neu,COUNT(bpx_kapitaldienstfaehigkeit_inkl_neu)),INDEX(bpy_kapitaldienstfaehigkeit_inkl_neu,MATCH(J6,bpx_kapitaldienstfaehigkeit_inkl_neu,1))+(J6-INDEX(bpx_kapitaldienstfaehigkeit_inkl_neu,MATCH(J6,bpx_kapitaldienstfaehigkeit_inkl_neu,1)))/(INDEX(bpx_kapitaldienstfaehigkeit_inkl_neu,MATCH(J6,bpx_kapitaldienstfaehigkeit_inkl_neu,1)+1)-INDEX(bpx_kapitaldienstfaehigkeit_inkl_neu,MATCH(J6,bpx_kapitaldienstfaehigkeit_inkl_neu,1)))*(INDEX(bpy_kapitaldienstfaehigkeit_inkl_neu,MATCH(J6,bpx_kapitaldienstfaehigkeit_inkl_neu,1)+1)-INDEX(bpy_kapitaldienstfaehigkeit_inkl_neu,MATCH(J6,bpx_kapitaldienstfaehigkeit_inkl_neu,1)))))) | L6: =IF(ISNUMBER(K6),$B6*K6,0) | M6: =IF(Kennzahlen!F38="","",Kennzahlen!F38) | N6: =IF(NOT(ISNUMBER(M6)),"",IF(M6<=INDEX(bpx_kapitaldienstfaehigkeit_inkl_neu,1),INDEX(bpy_kapitaldienstfaehigkeit_inkl_neu,1),IF(M6>=INDEX(bpx_kapitaldienstfaehigkeit_inkl_neu,COUNT(bpx_kapitaldienstfaehigkeit_inkl_neu)),INDEX(bpy_kapitaldienstfaehigkeit_inkl_neu,COUNT(bpx_kapitaldienstfaehigkeit_inkl_neu)),INDEX(bpy_kapitaldienstfaehigkeit_inkl_neu,MATCH(M6,bpx_kapitaldienstfaehigkeit_inkl_neu,1))+(M6-INDEX(bpx_kapitaldienstfaehigkeit_inkl_neu,MATCH(M6,bpx_kapitaldienstfaehigkeit_inkl_neu,1)))/(INDEX(bpx_kapitaldienstfaehigkeit_inkl_neu,MATCH(M6,bpx_kapitaldienstfaehigkeit_inkl_neu,1)+1)-INDEX(bpx_kapitaldienstfaehigkeit_inkl_neu,MATCH(M6,bpx_kapitaldienstfaehigkeit_inkl_neu,1)))*(INDEX(bpy_kapitaldienstfaehigkeit_inkl_neu,MATCH(M6,bpx_kapitaldienstfaehigkeit_inkl_neu,1)+1)-INDEX(bpy_kapitaldienstfaehigkeit_inkl_neu,MATCH(M6,bpx_kapitaldienstfaehigkeit_inkl_neu,1)))))) | O6: =IF(ISNUMBER(N6),$B6*N6,0) | P6: =IF(Kennzahlen!G38="","",Kennzahlen!G38) | Q6: =IF(NOT(ISNUMBER(P6)),"",IF(P6<=INDEX(bpx_kapitaldienstfaehigkeit_inkl_neu,1),INDEX(bpy_kapitaldienstfaehigkeit_inkl_neu,1),IF(P6>=INDEX(bpx_kapitaldienstfaehigkeit_inkl_neu,COUNT(bpx_kapitaldienstfaehigkeit_inkl_neu)),INDEX(bpy_kapitaldienstfaehigkeit_inkl_neu,COUNT(bpx_kapitaldienstfaehigkeit_inkl_neu)),INDEX(bpy_kapitaldienstfaehigkeit_inkl_neu,MATCH(P6,bpx_kapitaldienstfaehigkeit_inkl_neu,1))+(P6-INDEX(bpx_kapitaldienstfaehigkeit_inkl_neu,MATCH(P6,bpx_kapitaldienstfaehigkeit_inkl_neu,1)))/(INDEX(bpx_kapitaldienstfaehigkeit_inkl_neu,MATCH(P6,bpx_kapitaldienstfaehigkeit_inkl_neu,1)+1)-INDEX(bpx_kapitaldienstfaehigkeit_inkl_neu,MATCH(P6,bpx_kapitaldienstfaehigkeit_inkl_neu,1)))*(INDEX(bpy_kapitaldienstfaehigkeit_inkl_neu,MATCH(P6,bpx_kapitaldienstfaehigkeit_inkl_neu,1)+1)-INDEX(bpy_kapitaldienstfaehigkeit_inkl_neu,MATCH(P6,bpx_kapitaldienstfaehigkeit_inkl_neu,1)))))) | R6: =IF(ISNUMBER(Q6),$B6*Q6,0) | S6: =IF(Kennzahlen!H38="","",Kennzahlen!H38) | T6: =IF(NOT(ISNUMBER(S6)),"",IF(S6<=INDEX(bpx_kapitaldienstfaehigkeit_inkl_neu,1),INDEX(bpy_kapitaldienstfaehigkeit_inkl_neu,1),IF(S6>=INDEX(bpx_kapitaldienstfaehigkeit_inkl_neu,COUNT(bpx_kapitaldienstfaehigkeit_inkl_neu)),INDEX(bpy_kapitaldienstfaehigkeit_inkl_neu,COUNT(bpx_kapitaldienstfaehigkeit_inkl_neu)),INDEX(bpy_kapitaldienstfaehigkeit_inkl_neu,MATCH(S6,bpx_kapitaldienstfaehigkeit_inkl_neu,1))+(S6-INDEX(bpx_kapitaldienstfaehigkeit_inkl_neu,MATCH(S6,bpx_kapitaldienstfaehigkeit_inkl_neu,1)))/(INDEX(bpx_kapitaldienstfaehigkeit_inkl_neu,MATCH(S6,bpx_kapitaldienstfaehigkeit_inkl_neu,1)+1)-INDEX(bpx_kapitaldienstfaehigkeit_inkl_neu,MATCH(S6,bpx_kapitaldienstfaehigkeit_inkl_neu,1)))*(INDEX(bpy_kapitaldienstfaehigkeit_inkl_neu,MATCH(S6,bpx_kapitaldienstfaehigkeit_inkl_neu,1)+1)-INDEX(bpy_kapitaldienstfaehigkeit_inkl_neu,MATCH(S6,bpx_kapitaldienstfaehigkeit_inkl_neu,1)))))) | U6: =IF(ISNUMBER(T6),$B6*T6,0) | V6: =IF(Kennzahlen!I38="","",Kennzahlen!I38) | W6: =IF(NOT(ISNUMBER(V6)),"",IF(V6<=INDEX(bpx_kapitaldienstfaehigkeit_inkl_neu,1),INDEX(bpy_kapitaldienstfaehigkeit_inkl_neu,1),IF(V6>=INDEX(bpx_kapitaldienstfaehigkeit_inkl_neu,COUNT(bpx_kapitaldienstfaehigkeit_inkl_neu)),INDEX(bpy_kapitaldienstfaehigkeit_inkl_neu,COUNT(bpx_kapitaldienstfaehigkeit_inkl_neu)),INDEX(bpy_kapitaldienstfaehigkeit_inkl_neu,MATCH(V6,bpx_kapitaldienstfaehigkeit_inkl_neu,1))+(V6-INDEX(bpx_kapitaldienstfaehigkeit_inkl_neu,MATCH(V6,bpx_kapitaldienstfaehigkeit_inkl_neu,1)))/(INDEX(bpx_kapitaldienstfaehigkeit_inkl_neu,MATCH(V6,bpx_kapitaldienstfaehigkeit_inkl_neu,1)+1)-INDEX(bpx_kapitaldienstfaehigkeit_inkl_neu,MATCH(V6,bpx_kapitaldienstfaehigkeit_inkl_neu,1)))*(INDEX(bpy_kapitaldienstfaehigkeit_inkl_neu,MATCH(V6,bpx_kapitaldienstfaehigkeit_inkl_neu,1)+1)-INDEX(bpy_kapitaldienstfaehigkeit_inkl_neu,MATCH(V6,bpx_kapitaldienstfaehigkeit_inkl_neu,1)))))) | X6: =IF(ISNUMBER(W6),$B6*W6,0)
A7: Dynamischer Verschuldungsgrad (Nettoverschuldung / EBITDA) | B7: 0.15 | C7: x | D7: =IF(Kennzahlen!C36="","",Kennzahlen!C36) | E7: =IF(Kennzahlen!C22<=0,0,IF(NOT(ISNUMBER(D7)),"",IF(D7<=INDEX(bpx_dynamischer_verschuldungsgrad,1),INDEX(bpy_dynamischer_verschuldungsgrad,1),IF(D7>=INDEX(bpx_dynamischer_verschuldungsgrad,COUNT(bpx_dynamischer_verschuldungsgrad)),INDEX(bpy_dynamischer_verschuldungsgrad,COUNT(bpx_dynamischer_verschuldungsgrad)),INDEX(bpy_dynamischer_verschuldungsgrad,MATCH(D7,bpx_dynamischer_verschuldungsgrad,1))+(D7-INDEX(bpx_dynamischer_verschuldungsgrad,MATCH(D7,bpx_dynamischer_verschuldungsgrad,1)))/(INDEX(bpx_dynamischer_verschuldungsgrad,MATCH(D7,bpx_dynamischer_verschuldungsgrad,1)+1)-INDEX(bpx_dynamischer_verschuldungsgrad,MATCH(D7,bpx_dynamischer_verschuldungsgrad,1)))*(INDEX(bpy_dynamischer_verschuldungsgrad,MATCH(D7,bpx_dynamischer_verschuldungsgrad,1)+1)-INDEX(bpy_dynamischer_verschuldungsgrad,MATCH(D7,bpx_dynamischer_verschuldungsgrad,1))))))) | F7: =IF(ISNUMBER(E7),$B7*E7,0) | G7: =IF(Kennzahlen!D36="","",Kennzahlen!D36) | H7: =IF(Kennzahlen!D22<=0,0,IF(NOT(ISNUMBER(G7)),"",IF(G7<=INDEX(bpx_dynamischer_verschuldungsgrad,1),INDEX(bpy_dynamischer_verschuldungsgrad,1),IF(G7>=INDEX(bpx_dynamischer_verschuldungsgrad,COUNT(bpx_dynamischer_verschuldungsgrad)),INDEX(bpy_dynamischer_verschuldungsgrad,COUNT(bpx_dynamischer_verschuldungsgrad)),INDEX(bpy_dynamischer_verschuldungsgrad,MATCH(G7,bpx_dynamischer_verschuldungsgrad,1))+(G7-INDEX(bpx_dynamischer_verschuldungsgrad,MATCH(G7,bpx_dynamischer_verschuldungsgrad,1)))/(INDEX(bpx_dynamischer_verschuldungsgrad,MATCH(G7,bpx_dynamischer_verschuldungsgrad,1)+1)-INDEX(bpx_dynamischer_verschuldungsgrad,MATCH(G7,bpx_dynamischer_verschuldungsgrad,1)))*(INDEX(bpy_dynamischer_verschuldungsgrad,MATCH(G7,bpx_dynamischer_verschuldungsgrad,1)+1)-INDEX(bpy_dynamischer_verschuldungsgrad,MATCH(G7,bpx_dynamischer_verschuldungsgrad,1))))))) | I7: =IF(ISNUMBER(H7),$B7*H7,0) | J7: =IF(Kennzahlen!E36="","",Kennzahlen!E36) | K7: =IF(Kennzahlen!E22<=0,0,IF(NOT(ISNUMBER(J7)),"",IF(J7<=INDEX(bpx_dynamischer_verschuldungsgrad,1),INDEX(bpy_dynamischer_verschuldungsgrad,1),IF(J7>=INDEX(bpx_dynamischer_verschuldungsgrad,COUNT(bpx_dynamischer_verschuldungsgrad)),INDEX(bpy_dynamischer_verschuldungsgrad,COUNT(bpx_dynamischer_verschuldungsgrad)),INDEX(bpy_dynamischer_verschuldungsgrad,MATCH(J7,bpx_dynamischer_verschuldungsgrad,1))+(J7-INDEX(bpx_dynamischer_verschuldungsgrad,MATCH(J7,bpx_dynamischer_verschuldungsgrad,1)))/(INDEX(bpx_dynamischer_verschuldungsgrad,MATCH(J7,bpx_dynamischer_verschuldungsgrad,1)+1)-INDEX(bpx_dynamischer_verschuldungsgrad,MATCH(J7,bpx_dynamischer_verschuldungsgrad,1)))*(INDEX(bpy_dynamischer_verschuldungsgrad,MATCH(J7,bpx_dynamischer_verschuldungsgrad,1)+1)-INDEX(bpy_dynamischer_verschuldungsgrad,MATCH(J7,bpx_dynamischer_verschuldungsgrad,1))))))) | L7: =IF(ISNUMBER(K7),$B7*K7,0) | M7: =IF(Kennzahlen!F36="","",Kennzahlen!F36) | N7: =IF(Kennzahlen!F22<=0,0,IF(NOT(ISNUMBER(M7)),"",IF(M7<=INDEX(bpx_dynamischer_verschuldungsgrad,1),INDEX(bpy_dynamischer_verschuldungsgrad,1),IF(M7>=INDEX(bpx_dynamischer_verschuldungsgrad,COUNT(bpx_dynamischer_verschuldungsgrad)),INDEX(bpy_dynamischer_verschuldungsgrad,COUNT(bpx_dynamischer_verschuldungsgrad)),INDEX(bpy_dynamischer_verschuldungsgrad,MATCH(M7,bpx_dynamischer_verschuldungsgrad,1))+(M7-INDEX(bpx_dynamischer_verschuldungsgrad,MATCH(M7,bpx_dynamischer_verschuldungsgrad,1)))/(INDEX(bpx_dynamischer_verschuldungsgrad,MATCH(M7,bpx_dynamischer_verschuldungsgrad,1)+1)-INDEX(bpx_dynamischer_verschuldungsgrad,MATCH(M7,bpx_dynamischer_verschuldungsgrad,1)))*(INDEX(bpy_dynamischer_verschuldungsgrad,MATCH(M7,bpx_dynamischer_verschuldungsgrad,1)+1)-INDEX(bpy_dynamischer_verschuldungsgrad,MATCH(M7,bpx_dynamischer_verschuldungsgrad,1))))))) | O7: =IF(ISNUMBER(N7),$B7*N7,0) | P7: =IF(Kennzahlen!G36="","",Kennzahlen!G36) | Q7: =IF(Kennzahlen!G22<=0,0,IF(NOT(ISNUMBER(P7)),"",IF(P7<=INDEX(bpx_dynamischer_verschuldungsgrad,1),INDEX(bpy_dynamischer_verschuldungsgrad,1),IF(P7>=INDEX(bpx_dynamischer_verschuldungsgrad,COUNT(bpx_dynamischer_verschuldungsgrad)),INDEX(bpy_dynamischer_verschuldungsgrad,COUNT(bpx_dynamischer_verschuldungsgrad)),INDEX(bpy_dynamischer_verschuldungsgrad,MATCH(P7,bpx_dynamischer_verschuldungsgrad,1))+(P7-INDEX(bpx_dynamischer_verschuldungsgrad,MATCH(P7,bpx_dynamischer_verschuldungsgrad,1)))/(INDEX(bpx_dynamischer_verschuldungsgrad,MATCH(P7,bpx_dynamischer_verschuldungsgrad,1)+1)-INDEX(bpx_dynamischer_verschuldungsgrad,MATCH(P7,bpx_dynamischer_verschuldungsgrad,1)))*(INDEX(bpy_dynamischer_verschuldungsgrad,MATCH(P7,bpx_dynamischer_verschuldungsgrad,1)+1)-INDEX(bpy_dynamischer_verschuldungsgrad,MATCH(P7,bpx_dynamischer_verschuldungsgrad,1))))))) | R7: =IF(ISNUMBER(Q7),$B7*Q7,0) | S7: =IF(Kennzahlen!H36="","",Kennzahlen!H36) | T7: =IF(Kennzahlen!H22<=0,0,IF(NOT(ISNUMBER(S7)),"",IF(S7<=INDEX(bpx_dynamischer_verschuldungsgrad,1),INDEX(bpy_dynamischer_verschuldungsgrad,1),IF(S7>=INDEX(bpx_dynamischer_verschuldungsgrad,COUNT(bpx_dynamischer_verschuldungsgrad)),INDEX(bpy_dynamischer_verschuldungsgrad,COUNT(bpx_dynamischer_verschuldungsgrad)),INDEX(bpy_dynamischer_verschuldungsgrad,MATCH(S7,bpx_dynamischer_verschuldungsgrad,1))+(S7-INDEX(bpx_dynamischer_verschuldungsgrad,MATCH(S7,bpx_dynamischer_verschuldungsgrad,1)))/(INDEX(bpx_dynamischer_verschuldungsgrad,MATCH(S7,bpx_dynamischer_verschuldungsgrad,1)+1)-INDEX(bpx_dynamischer_verschuldungsgrad,MATCH(S7,bpx_dynamischer_verschuldungsgrad,1)))*(INDEX(bpy_dynamischer_verschuldungsgrad,MATCH(S7,bpx_dynamischer_verschuldungsgrad,1)+1)-INDEX(bpy_dynamischer_verschuldungsgrad,MATCH(S7,bpx_dynamischer_verschuldungsgrad,1))))))) | U7: =IF(ISNUMBER(T7),$B7*T7,0) | V7: =IF(Kennzahlen!I36="","",Kennzahlen!I36) | W7: =IF(Kennzahlen!I22<=0,0,IF(NOT(ISNUMBER(V7)),"",IF(V7<=INDEX(bpx_dynamischer_verschuldungsgrad,1),INDEX(bpy_dynamischer_verschuldungsgrad,1),IF(V7>=INDEX(bpx_dynamischer_verschuldungsgrad,COUNT(bpx_dynamischer_verschuldungsgrad)),INDEX(bpy_dynamischer_verschuldungsgrad,COUNT(bpx_dynamischer_verschuldungsgrad)),INDEX(bpy_dynamischer_verschuldungsgrad,MATCH(V7,bpx_dynamischer_verschuldungsgrad,1))+(V7-INDEX(bpx_dynamischer_verschuldungsgrad,MATCH(V7,bpx_dynamischer_verschuldungsgrad,1)))/(INDEX(bpx_dynamischer_verschuldungsgrad,MATCH(V7,bpx_dynamischer_verschuldungsgrad,1)+1)-INDEX(bpx_dynamischer_verschuldungsgrad,MATCH(V7,bpx_dynamischer_verschuldungsgrad,1)))*(INDEX(bpy_dynamischer_verschuldungsgrad,MATCH(V7,bpx_dynamischer_verschuldungsgrad,1)+1)-INDEX(bpy_dynamischer_verschuldungsgrad,MATCH(V7,bpx_dynamischer_verschuldungsgrad,1))))))) | X7: =IF(ISNUMBER(W7),$B7*W7,0)
A8: EBIT-Marge | B8: 0.12 | C8: percent | D8: =IF(Kennzahlen!C41="","",Kennzahlen!C41) | E8: =IF(NOT(ISNUMBER(D8)),"",IF(D8<=INDEX(bpx_ebit_marge,1),INDEX(bpy_ebit_marge,1),IF(D8>=INDEX(bpx_ebit_marge,COUNT(bpx_ebit_marge)),INDEX(bpy_ebit_marge,COUNT(bpx_ebit_marge)),INDEX(bpy_ebit_marge,MATCH(D8,bpx_ebit_marge,1))+(D8-INDEX(bpx_ebit_marge,MATCH(D8,bpx_ebit_marge,1)))/(INDEX(bpx_ebit_marge,MATCH(D8,bpx_ebit_marge,1)+1)-INDEX(bpx_ebit_marge,MATCH(D8,bpx_ebit_marge,1)))*(INDEX(bpy_ebit_marge,MATCH(D8,bpx_ebit_marge,1)+1)-INDEX(bpy_ebit_marge,MATCH(D8,bpx_ebit_marge,1)))))) | F8: =IF(ISNUMBER(E8),$B8*E8,0) | G8: =IF(Kennzahlen!D41="","",Kennzahlen!D41) | H8: =IF(NOT(ISNUMBER(G8)),"",IF(G8<=INDEX(bpx_ebit_marge,1),INDEX(bpy_ebit_marge,1),IF(G8>=INDEX(bpx_ebit_marge,COUNT(bpx_ebit_marge)),INDEX(bpy_ebit_marge,COUNT(bpx_ebit_marge)),INDEX(bpy_ebit_marge,MATCH(G8,bpx_ebit_marge,1))+(G8-INDEX(bpx_ebit_marge,MATCH(G8,bpx_ebit_marge,1)))/(INDEX(bpx_ebit_marge,MATCH(G8,bpx_ebit_marge,1)+1)-INDEX(bpx_ebit_marge,MATCH(G8,bpx_ebit_marge,1)))*(INDEX(bpy_ebit_marge,MATCH(G8,bpx_ebit_marge,1)+1)-INDEX(bpy_ebit_marge,MATCH(G8,bpx_ebit_marge,1)))))) | I8: =IF(ISNUMBER(H8),$B8*H8,0) | J8: =IF(Kennzahlen!E41="","",Kennzahlen!E41) | K8: =IF(NOT(ISNUMBER(J8)),"",IF(J8<=INDEX(bpx_ebit_marge,1),INDEX(bpy_ebit_marge,1),IF(J8>=INDEX(bpx_ebit_marge,COUNT(bpx_ebit_marge)),INDEX(bpy_ebit_marge,COUNT(bpx_ebit_marge)),INDEX(bpy_ebit_marge,MATCH(J8,bpx_ebit_marge,1))+(J8-INDEX(bpx_ebit_marge,MATCH(J8,bpx_ebit_marge,1)))/(INDEX(bpx_ebit_marge,MATCH(J8,bpx_ebit_marge,1)+1)-INDEX(bpx_ebit_marge,MATCH(J8,bpx_ebit_marge,1)))*(INDEX(bpy_ebit_marge,MATCH(J8,bpx_ebit_marge,1)+1)-INDEX(bpy_ebit_marge,MATCH(J8,bpx_ebit_marge,1)))))) | L8: =IF(ISNUMBER(K8),$B8*K8,0) | M8: =IF(Kennzahlen!F41="","",Kennzahlen!F41) | N8: =IF(NOT(ISNUMBER(M8)),"",IF(M8<=INDEX(bpx_ebit_marge,1),INDEX(bpy_ebit_marge,1),IF(M8>=INDEX(bpx_ebit_marge,COUNT(bpx_ebit_marge)),INDEX(bpy_ebit_marge,COUNT(bpx_ebit_marge)),INDEX(bpy_ebit_marge,MATCH(M8,bpx_ebit_marge,1))+(M8-INDEX(bpx_ebit_marge,MATCH(M8,bpx_ebit_marge,1)))/(INDEX(bpx_ebit_marge,MATCH(M8,bpx_ebit_marge,1)+1)-INDEX(bpx_ebit_marge,MATCH(M8,bpx_ebit_marge,1)))*(INDEX(bpy_ebit_marge,MATCH(M8,bpx_ebit_marge,1)+1)-INDEX(bpy_ebit_marge,MATCH(M8,bpx_ebit_marge,1)))))) | O8: =IF(ISNUMBER(N8),$B8*N8,0) | P8: =IF(Kennzahlen!G41="","",Kennzahlen!G41) | Q8: =IF(NOT(ISNUMBER(P8)),"",IF(P8<=INDEX(bpx_ebit_marge,1),INDEX(bpy_ebit_marge,1),IF(P8>=INDEX(bpx_ebit_marge,COUNT(bpx_ebit_marge)),INDEX(bpy_ebit_marge,COUNT(bpx_ebit_marge)),INDEX(bpy_ebit_marge,MATCH(P8,bpx_ebit_marge,1))+(P8-INDEX(bpx_ebit_marge,MATCH(P8,bpx_ebit_marge,1)))/(INDEX(bpx_ebit_marge,MATCH(P8,bpx_ebit_marge,1)+1)-INDEX(bpx_ebit_marge,MATCH(P8,bpx_ebit_marge,1)))*(INDEX(bpy_ebit_marge,MATCH(P8,bpx_ebit_marge,1)+1)-INDEX(bpy_ebit_marge,MATCH(P8,bpx_ebit_marge,1)))))) | R8: =IF(ISNUMBER(Q8),$B8*Q8,0) | S8: =IF(Kennzahlen!H41="","",Kennzahlen!H41) | T8: =IF(NOT(ISNUMBER(S8)),"",IF(S8<=INDEX(bpx_ebit_marge,1),INDEX(bpy_ebit_marge,1),IF(S8>=INDEX(bpx_ebit_marge,COUNT(bpx_ebit_marge)),INDEX(bpy_ebit_marge,COUNT(bpx_ebit_marge)),INDEX(bpy_ebit_marge,MATCH(S8,bpx_ebit_marge,1))+(S8-INDEX(bpx_ebit_marge,MATCH(S8,bpx_ebit_marge,1)))/(INDEX(bpx_ebit_marge,MATCH(S8,bpx_ebit_marge,1)+1)-INDEX(bpx_ebit_marge,MATCH(S8,bpx_ebit_marge,1)))*(INDEX(bpy_ebit_marge,MATCH(S8,bpx_ebit_marge,1)+1)-INDEX(bpy_ebit_marge,MATCH(S8,bpx_ebit_marge,1)))))) | U8: =IF(ISNUMBER(T8),$B8*T8,0) | V8: =IF(Kennzahlen!I41="","",Kennzahlen!I41) | W8: =IF(NOT(ISNUMBER(V8)),"",IF(V8<=INDEX(bpx_ebit_marge,1),INDEX(bpy_ebit_marge,1),IF(V8>=INDEX(bpx_ebit_marge,COUNT(bpx_ebit_marge)),INDEX(bpy_ebit_marge,COUNT(bpx_ebit_marge)),INDEX(bpy_ebit_marge,MATCH(V8,bpx_ebit_marge,1))+(V8-INDEX(bpx_ebit_marge,MATCH(V8,bpx_ebit_marge,1)))/(INDEX(bpx_ebit_marge,MATCH(V8,bpx_ebit_marge,1)+1)-INDEX(bpx_ebit_marge,MATCH(V8,bpx_ebit_marge,1)))*(INDEX(bpy_ebit_marge,MATCH(V8,bpx_ebit_marge,1)+1)-INDEX(bpy_ebit_marge,MATCH(V8,bpx_ebit_marge,1)))))) | X8: =IF(ISNUMBER(W8),$B8*W8,0)
A9: Liquiditaet 2. Grades | B9: 0.08 | C9: percent | D9: =IF(Kennzahlen!C44="","",Kennzahlen!C44) | E9: =IF(NOT(ISNUMBER(D9)),"",IF(D9<=INDEX(bpx_liquiditaet_2_grades,1),INDEX(bpy_liquiditaet_2_grades,1),IF(D9>=INDEX(bpx_liquiditaet_2_grades,COUNT(bpx_liquiditaet_2_grades)),INDEX(bpy_liquiditaet_2_grades,COUNT(bpx_liquiditaet_2_grades)),INDEX(bpy_liquiditaet_2_grades,MATCH(D9,bpx_liquiditaet_2_grades,1))+(D9-INDEX(bpx_liquiditaet_2_grades,MATCH(D9,bpx_liquiditaet_2_grades,1)))/(INDEX(bpx_liquiditaet_2_grades,MATCH(D9,bpx_liquiditaet_2_grades,1)+1)-INDEX(bpx_liquiditaet_2_grades,MATCH(D9,bpx_liquiditaet_2_grades,1)))*(INDEX(bpy_liquiditaet_2_grades,MATCH(D9,bpx_liquiditaet_2_grades,1)+1)-INDEX(bpy_liquiditaet_2_grades,MATCH(D9,bpx_liquiditaet_2_grades,1)))))) | F9: =IF(ISNUMBER(E9),$B9*E9,0) | G9: =IF(Kennzahlen!D44="","",Kennzahlen!D44) | H9: =IF(NOT(ISNUMBER(G9)),"",IF(G9<=INDEX(bpx_liquiditaet_2_grades,1),INDEX(bpy_liquiditaet_2_grades,1),IF(G9>=INDEX(bpx_liquiditaet_2_grades,COUNT(bpx_liquiditaet_2_grades)),INDEX(bpy_liquiditaet_2_grades,COUNT(bpx_liquiditaet_2_grades)),INDEX(bpy_liquiditaet_2_grades,MATCH(G9,bpx_liquiditaet_2_grades,1))+(G9-INDEX(bpx_liquiditaet_2_grades,MATCH(G9,bpx_liquiditaet_2_grades,1)))/(INDEX(bpx_liquiditaet_2_grades,MATCH(G9,bpx_liquiditaet_2_grades,1)+1)-INDEX(bpx_liquiditaet_2_grades,MATCH(G9,bpx_liquiditaet_2_grades,1)))*(INDEX(bpy_liquiditaet_2_grades,MATCH(G9,bpx_liquiditaet_2_grades,1)+1)-INDEX(bpy_liquiditaet_2_grades,MATCH(G9,bpx_liquiditaet_2_grades,1)))))) | I9: =IF(ISNUMBER(H9),$B9*H9,0) | J9: =IF(Kennzahlen!E44="","",Kennzahlen!E44) | K9: =IF(NOT(ISNUMBER(J9)),"",IF(J9<=INDEX(bpx_liquiditaet_2_grades,1),INDEX(bpy_liquiditaet_2_grades,1),IF(J9>=INDEX(bpx_liquiditaet_2_grades,COUNT(bpx_liquiditaet_2_grades)),INDEX(bpy_liquiditaet_2_grades,COUNT(bpx_liquiditaet_2_grades)),INDEX(bpy_liquiditaet_2_grades,MATCH(J9,bpx_liquiditaet_2_grades,1))+(J9-INDEX(bpx_liquiditaet_2_grades,MATCH(J9,bpx_liquiditaet_2_grades,1)))/(INDEX(bpx_liquiditaet_2_grades,MATCH(J9,bpx_liquiditaet_2_grades,1)+1)-INDEX(bpx_liquiditaet_2_grades,MATCH(J9,bpx_liquiditaet_2_grades,1)))*(INDEX(bpy_liquiditaet_2_grades,MATCH(J9,bpx_liquiditaet_2_grades,1)+1)-INDEX(bpy_liquiditaet_2_grades,MATCH(J9,bpx_liquiditaet_2_grades,1)))))) | L9: =IF(ISNUMBER(K9),$B9*K9,0) | M9: =IF(Kennzahlen!F44="","",Kennzahlen!F44) | N9: =IF(NOT(ISNUMBER(M9)),"",IF(M9<=INDEX(bpx_liquiditaet_2_grades,1),INDEX(bpy_liquiditaet_2_grades,1),IF(M9>=INDEX(bpx_liquiditaet_2_grades,COUNT(bpx_liquiditaet_2_grades)),INDEX(bpy_liquiditaet_2_grades,COUNT(bpx_liquiditaet_2_grades)),INDEX(bpy_liquiditaet_2_grades,MATCH(M9,bpx_liquiditaet_2_grades,1))+(M9-INDEX(bpx_liquiditaet_2_grades,MATCH(M9,bpx_liquiditaet_2_grades,1)))/(INDEX(bpx_liquiditaet_2_grades,MATCH(M9,bpx_liquiditaet_2_grades,1)+1)-INDEX(bpx_liquiditaet_2_grades,MATCH(M9,bpx_liquiditaet_2_grades,1)))*(INDEX(bpy_liquiditaet_2_grades,MATCH(M9,bpx_liquiditaet_2_grades,1)+1)-INDEX(bpy_liquiditaet_2_grades,MATCH(M9,bpx_liquiditaet_2_grades,1)))))) | O9: =IF(ISNUMBER(N9),$B9*N9,0) | P9: =IF(Kennzahlen!G44="","",Kennzahlen!G44) | Q9: =IF(NOT(ISNUMBER(P9)),"",IF(P9<=INDEX(bpx_liquiditaet_2_grades,1),INDEX(bpy_liquiditaet_2_grades,1),IF(P9>=INDEX(bpx_liquiditaet_2_grades,COUNT(bpx_liquiditaet_2_grades)),INDEX(bpy_liquiditaet_2_grades,COUNT(bpx_liquiditaet_2_grades)),INDEX(bpy_liquiditaet_2_grades,MATCH(P9,bpx_liquiditaet_2_grades,1))+(P9-INDEX(bpx_liquiditaet_2_grades,MATCH(P9,bpx_liquiditaet_2_grades,1)))/(INDEX(bpx_liquiditaet_2_grades,MATCH(P9,bpx_liquiditaet_2_grades,1)+1)-INDEX(bpx_liquiditaet_2_grades,MATCH(P9,bpx_liquiditaet_2_grades,1)))*(INDEX(bpy_liquiditaet_2_grades,MATCH(P9,bpx_liquiditaet_2_grades,1)+1)-INDEX(bpy_liquiditaet_2_grades,MATCH(P9,bpx_liquiditaet_2_grades,1)))))) | R9: =IF(ISNUMBER(Q9),$B9*Q9,0) | S9: =IF(Kennzahlen!H44="","",Kennzahlen!H44) | T9: =IF(NOT(ISNUMBER(S9)),"",IF(S9<=INDEX(bpx_liquiditaet_2_grades,1),INDEX(bpy_liquiditaet_2_grades,1),IF(S9>=INDEX(bpx_liquiditaet_2_grades,COUNT(bpx_liquiditaet_2_grades)),INDEX(bpy_liquiditaet_2_grades,COUNT(bpx_liquiditaet_2_grades)),INDEX(bpy_liquiditaet_2_grades,MATCH(S9,bpx_liquiditaet_2_grades,1))+(S9-INDEX(bpx_liquiditaet_2_grades,MATCH(S9,bpx_liquiditaet_2_grades,1)))/(INDEX(bpx_liquiditaet_2_grades,MATCH(S9,bpx_liquiditaet_2_grades,1)+1)-INDEX(bpx_liquiditaet_2_grades,MATCH(S9,bpx_liquiditaet_2_grades,1)))*(INDEX(bpy_liquiditaet_2_grades,MATCH(S9,bpx_liquiditaet_2_grades,1)+1)-INDEX(bpy_liquiditaet_2_grades,MATCH(S9,bpx_liquiditaet_2_grades,1)))))) | U9: =IF(ISNUMBER(T9),$B9*T9,0) | V9: =IF(Kennzahlen!I44="","",Kennzahlen!I44) | W9: =IF(NOT(ISNUMBER(V9)),"",IF(V9<=INDEX(bpx_liquiditaet_2_grades,1),INDEX(bpy_liquiditaet_2_grades,1),IF(V9>=INDEX(bpx_liquiditaet_2_grades,COUNT(bpx_liquiditaet_2_grades)),INDEX(bpy_liquiditaet_2_grades,COUNT(bpx_liquiditaet_2_grades)),INDEX(bpy_liquiditaet_2_grades,MATCH(V9,bpx_liquiditaet_2_grades,1))+(V9-INDEX(bpx_liquiditaet_2_grades,MATCH(V9,bpx_liquiditaet_2_grades,1)))/(INDEX(bpx_liquiditaet_2_grades,MATCH(V9,bpx_liquiditaet_2_grades,1)+1)-INDEX(bpx_liquiditaet_2_grades,MATCH(V9,bpx_liquiditaet_2_grades,1)))*(INDEX(bpy_liquiditaet_2_grades,MATCH(V9,bpx_liquiditaet_2_grades,1)+1)-INDEX(bpy_liquiditaet_2_grades,MATCH(V9,bpx_liquiditaet_2_grades,1)))))) | X9: =IF(ISNUMBER(W9),$B9*W9,0)
A10: Zinsdeckungsgrad (EBIT / Zinsaufwand) | B10: 0.05 | C10: x | D10: =IF(Kennzahlen!C39="","",Kennzahlen!C39) | E10: =IF(NOT(ISNUMBER(D10)),"",IF(D10<=INDEX(bpx_zinsdeckungsgrad,1),INDEX(bpy_zinsdeckungsgrad,1),IF(D10>=INDEX(bpx_zinsdeckungsgrad,COUNT(bpx_zinsdeckungsgrad)),INDEX(bpy_zinsdeckungsgrad,COUNT(bpx_zinsdeckungsgrad)),INDEX(bpy_zinsdeckungsgrad,MATCH(D10,bpx_zinsdeckungsgrad,1))+(D10-INDEX(bpx_zinsdeckungsgrad,MATCH(D10,bpx_zinsdeckungsgrad,1)))/(INDEX(bpx_zinsdeckungsgrad,MATCH(D10,bpx_zinsdeckungsgrad,1)+1)-INDEX(bpx_zinsdeckungsgrad,MATCH(D10,bpx_zinsdeckungsgrad,1)))*(INDEX(bpy_zinsdeckungsgrad,MATCH(D10,bpx_zinsdeckungsgrad,1)+1)-INDEX(bpy_zinsdeckungsgrad,MATCH(D10,bpx_zinsdeckungsgrad,1)))))) | F10: =IF(ISNUMBER(E10),$B10*E10,0) | G10: =IF(Kennzahlen!D39="","",Kennzahlen!D39) | H10: =IF(NOT(ISNUMBER(G10)),"",IF(G10<=INDEX(bpx_zinsdeckungsgrad,1),INDEX(bpy_zinsdeckungsgrad,1),IF(G10>=INDEX(bpx_zinsdeckungsgrad,COUNT(bpx_zinsdeckungsgrad)),INDEX(bpy_zinsdeckungsgrad,COUNT(bpx_zinsdeckungsgrad)),INDEX(bpy_zinsdeckungsgrad,MATCH(G10,bpx_zinsdeckungsgrad,1))+(G10-INDEX(bpx_zinsdeckungsgrad,MATCH(G10,bpx_zinsdeckungsgrad,1)))/(INDEX(bpx_zinsdeckungsgrad,MATCH(G10,bpx_zinsdeckungsgrad,1)+1)-INDEX(bpx_zinsdeckungsgrad,MATCH(G10,bpx_zinsdeckungsgrad,1)))*(INDEX(bpy_zinsdeckungsgrad,MATCH(G10,bpx_zinsdeckungsgrad,1)+1)-INDEX(bpy_zinsdeckungsgrad,MATCH(G10,bpx_zinsdeckungsgrad,1)))))) | I10: =IF(ISNUMBER(H10),$B10*H10,0) | J10: =IF(Kennzahlen!E39="","",Kennzahlen!E39) | K10: =IF(NOT(ISNUMBER(J10)),"",IF(J10<=INDEX(bpx_zinsdeckungsgrad,1),INDEX(bpy_zinsdeckungsgrad,1),IF(J10>=INDEX(bpx_zinsdeckungsgrad,COUNT(bpx_zinsdeckungsgrad)),INDEX(bpy_zinsdeckungsgrad,COUNT(bpx_zinsdeckungsgrad)),INDEX(bpy_zinsdeckungsgrad,MATCH(J10,bpx_zinsdeckungsgrad,1))+(J10-INDEX(bpx_zinsdeckungsgrad,MATCH(J10,bpx_zinsdeckungsgrad,1)))/(INDEX(bpx_zinsdeckungsgrad,MATCH(J10,bpx_zinsdeckungsgrad,1)+1)-INDEX(bpx_zinsdeckungsgrad,MATCH(J10,bpx_zinsdeckungsgrad,1)))*(INDEX(bpy_zinsdeckungsgrad,MATCH(J10,bpx_zinsdeckungsgrad,1)+1)-INDEX(bpy_zinsdeckungsgrad,MATCH(J10,bpx_zinsdeckungsgrad,1)))))) | L10: =IF(ISNUMBER(K10),$B10*K10,0) | M10: =IF(Kennzahlen!F39="","",Kennzahlen!F39) | N10: =IF(NOT(ISNUMBER(M10)),"",IF(M10<=INDEX(bpx_zinsdeckungsgrad,1),INDEX(bpy_zinsdeckungsgrad,1),IF(M10>=INDEX(bpx_zinsdeckungsgrad,COUNT(bpx_zinsdeckungsgrad)),INDEX(bpy_zinsdeckungsgrad,COUNT(bpx_zinsdeckungsgrad)),INDEX(bpy_zinsdeckungsgrad,MATCH(M10,bpx_zinsdeckungsgrad,1))+(M10-INDEX(bpx_zinsdeckungsgrad,MATCH(M10,bpx_zinsdeckungsgrad,1)))/(INDEX(bpx_zinsdeckungsgrad,MATCH(M10,bpx_zinsdeckungsgrad,1)+1)-INDEX(bpx_zinsdeckungsgrad,MATCH(M10,bpx_zinsdeckungsgrad,1)))*(INDEX(bpy_zinsdeckungsgrad,MATCH(M10,bpx_zinsdeckungsgrad,1)+1)-INDEX(bpy_zinsdeckungsgrad,MATCH(M10,bpx_zinsdeckungsgrad,1)))))) | O10: =IF(ISNUMBER(N10),$B10*N10,0) | P10: =IF(Kennzahlen!G39="","",Kennzahlen!G39) | Q10: =IF(NOT(ISNUMBER(P10)),"",IF(P10<=INDEX(bpx_zinsdeckungsgrad,1),INDEX(bpy_zinsdeckungsgrad,1),IF(P10>=INDEX(bpx_zinsdeckungsgrad,COUNT(bpx_zinsdeckungsgrad)),INDEX(bpy_zinsdeckungsgrad,COUNT(bpx_zinsdeckungsgrad)),INDEX(bpy_zinsdeckungsgrad,MATCH(P10,bpx_zinsdeckungsgrad,1))+(P10-INDEX(bpx_zinsdeckungsgrad,MATCH(P10,bpx_zinsdeckungsgrad,1)))/(INDEX(bpx_zinsdeckungsgrad,MATCH(P10,bpx_zinsdeckungsgrad,1)+1)-INDEX(bpx_zinsdeckungsgrad,MATCH(P10,bpx_zinsdeckungsgrad,1)))*(INDEX(bpy_zinsdeckungsgrad,MATCH(P10,bpx_zinsdeckungsgrad,1)+1)-INDEX(bpy_zinsdeckungsgrad,MATCH(P10,bpx_zinsdeckungsgrad,1)))))) | R10: =IF(ISNUMBER(Q10),$B10*Q10,0) | S10: =IF(Kennzahlen!H39="","",Kennzahlen!H39) | T10: =IF(NOT(ISNUMBER(S10)),"",IF(S10<=INDEX(bpx_zinsdeckungsgrad,1),INDEX(bpy_zinsdeckungsgrad,1),IF(S10>=INDEX(bpx_zinsdeckungsgrad,COUNT(bpx_zinsdeckungsgrad)),INDEX(bpy_zinsdeckungsgrad,COUNT(bpx_zinsdeckungsgrad)),INDEX(bpy_zinsdeckungsgrad,MATCH(S10,bpx_zinsdeckungsgrad,1))+(S10-INDEX(bpx_zinsdeckungsgrad,MATCH(S10,bpx_zinsdeckungsgrad,1)))/(INDEX(bpx_zinsdeckungsgrad,MATCH(S10,bpx_zinsdeckungsgrad,1)+1)-INDEX(bpx_zinsdeckungsgrad,MATCH(S10,bpx_zinsdeckungsgrad,1)))*(INDEX(bpy_zinsdeckungsgrad,MATCH(S10,bpx_zinsdeckungsgrad,1)+1)-INDEX(bpy_zinsdeckungsgrad,MATCH(S10,bpx_zinsdeckungsgrad,1)))))) | U10: =IF(ISNUMBER(T10),$B10*T10,0) | V10: =IF(Kennzahlen!I39="","",Kennzahlen!I39) | W10: =IF(NOT(ISNUMBER(V10)),"",IF(V10<=INDEX(bpx_zinsdeckungsgrad,1),INDEX(bpy_zinsdeckungsgrad,1),IF(V10>=INDEX(bpx_zinsdeckungsgrad,COUNT(bpx_zinsdeckungsgrad)),INDEX(bpy_zinsdeckungsgrad,COUNT(bpx_zinsdeckungsgrad)),INDEX(bpy_zinsdeckungsgrad,MATCH(V10,bpx_zinsdeckungsgrad,1))+(V10-INDEX(bpx_zinsdeckungsgrad,MATCH(V10,bpx_zinsdeckungsgrad,1)))/(INDEX(bpx_zinsdeckungsgrad,MATCH(V10,bpx_zinsdeckungsgrad,1)+1)-INDEX(bpx_zinsdeckungsgrad,MATCH(V10,bpx_zinsdeckungsgrad,1)))*(INDEX(bpy_zinsdeckungsgrad,MATCH(V10,bpx_zinsdeckungsgrad,1)+1)-INDEX(bpy_zinsdeckungsgrad,MATCH(V10,bpx_zinsdeckungsgrad,1)))))) | X10: =IF(ISNUMBER(W10),$B10*W10,0)
A11: Kontokorrent-Auslastung | B11: 0.06 | C11: percent | D11: =IF(Kennzahlen!C51="","",Kennzahlen!C51) | E11: =IF(NOT(ISNUMBER(D11)),"",IF(D11<=INDEX(bpx_kontokorrent_auslastung,1),INDEX(bpy_kontokorrent_auslastung,1),IF(D11>=INDEX(bpx_kontokorrent_auslastung,COUNT(bpx_kontokorrent_auslastung)),INDEX(bpy_kontokorrent_auslastung,COUNT(bpx_kontokorrent_auslastung)),INDEX(bpy_kontokorrent_auslastung,MATCH(D11,bpx_kontokorrent_auslastung,1))+(D11-INDEX(bpx_kontokorrent_auslastung,MATCH(D11,bpx_kontokorrent_auslastung,1)))/(INDEX(bpx_kontokorrent_auslastung,MATCH(D11,bpx_kontokorrent_auslastung,1)+1)-INDEX(bpx_kontokorrent_auslastung,MATCH(D11,bpx_kontokorrent_auslastung,1)))*(INDEX(bpy_kontokorrent_auslastung,MATCH(D11,bpx_kontokorrent_auslastung,1)+1)-INDEX(bpy_kontokorrent_auslastung,MATCH(D11,bpx_kontokorrent_auslastung,1)))))) | F11: =IF(ISNUMBER(E11),$B11*E11,0) | G11: =IF(Kennzahlen!D51="","",Kennzahlen!D51) | H11: =IF(NOT(ISNUMBER(G11)),"",IF(G11<=INDEX(bpx_kontokorrent_auslastung,1),INDEX(bpy_kontokorrent_auslastung,1),IF(G11>=INDEX(bpx_kontokorrent_auslastung,COUNT(bpx_kontokorrent_auslastung)),INDEX(bpy_kontokorrent_auslastung,COUNT(bpx_kontokorrent_auslastung)),INDEX(bpy_kontokorrent_auslastung,MATCH(G11,bpx_kontokorrent_auslastung,1))+(G11-INDEX(bpx_kontokorrent_auslastung,MATCH(G11,bpx_kontokorrent_auslastung,1)))/(INDEX(bpx_kontokorrent_auslastung,MATCH(G11,bpx_kontokorrent_auslastung,1)+1)-INDEX(bpx_kontokorrent_auslastung,MATCH(G11,bpx_kontokorrent_auslastung,1)))*(INDEX(bpy_kontokorrent_auslastung,MATCH(G11,bpx_kontokorrent_auslastung,1)+1)-INDEX(bpy_kontokorrent_auslastung,MATCH(G11,bpx_kontokorrent_auslastung,1)))))) | I11: =IF(ISNUMBER(H11),$B11*H11,0) | J11: =IF(Kennzahlen!E51="","",Kennzahlen!E51) | K11: =IF(NOT(ISNUMBER(J11)),"",IF(J11<=INDEX(bpx_kontokorrent_auslastung,1),INDEX(bpy_kontokorrent_auslastung,1),IF(J11>=INDEX(bpx_kontokorrent_auslastung,COUNT(bpx_kontokorrent_auslastung)),INDEX(bpy_kontokorrent_auslastung,COUNT(bpx_kontokorrent_auslastung)),INDEX(bpy_kontokorrent_auslastung,MATCH(J11,bpx_kontokorrent_auslastung,1))+(J11-INDEX(bpx_kontokorrent_auslastung,MATCH(J11,bpx_kontokorrent_auslastung,1)))/(INDEX(bpx_kontokorrent_auslastung,MATCH(J11,bpx_kontokorrent_auslastung,1)+1)-INDEX(bpx_kontokorrent_auslastung,MATCH(J11,bpx_kontokorrent_auslastung,1)))*(INDEX(bpy_kontokorrent_auslastung,MATCH(J11,bpx_kontokorrent_auslastung,1)+1)-INDEX(bpy_kontokorrent_auslastung,MATCH(J11,bpx_kontokorrent_auslastung,1)))))) | L11: =IF(ISNUMBER(K11),$B11*K11,0) | M11: =IF(Kennzahlen!F51="","",Kennzahlen!F51) | N11: =IF(NOT(ISNUMBER(M11)),"",IF(M11<=INDEX(bpx_kontokorrent_auslastung,1),INDEX(bpy_kontokorrent_auslastung,1),IF(M11>=INDEX(bpx_kontokorrent_auslastung,COUNT(bpx_kontokorrent_auslastung)),INDEX(bpy_kontokorrent_auslastung,COUNT(bpx_kontokorrent_auslastung)),INDEX(bpy_kontokorrent_auslastung,MATCH(M11,bpx_kontokorrent_auslastung,1))+(M11-INDEX(bpx_kontokorrent_auslastung,MATCH(M11,bpx_kontokorrent_auslastung,1)))/(INDEX(bpx_kontokorrent_auslastung,MATCH(M11,bpx_kontokorrent_auslastung,1)+1)-INDEX(bpx_kontokorrent_auslastung,MATCH(M11,bpx_kontokorrent_auslastung,1)))*(INDEX(bpy_kontokorrent_auslastung,MATCH(M11,bpx_kontokorrent_auslastung,1)+1)-INDEX(bpy_kontokorrent_auslastung,MATCH(M11,bpx_kontokorrent_auslastung,1)))))) | O11: =IF(ISNUMBER(N11),$B11*N11,0) | P11: =IF(Kennzahlen!G51="","",Kennzahlen!G51) | Q11: =IF(NOT(ISNUMBER(P11)),"",IF(P11<=INDEX(bpx_kontokorrent_auslastung,1),INDEX(bpy_kontokorrent_auslastung,1),IF(P11>=INDEX(bpx_kontokorrent_auslastung,COUNT(bpx_kontokorrent_auslastung)),INDEX(bpy_kontokorrent_auslastung,COUNT(bpx_kontokorrent_auslastung)),INDEX(bpy_kontokorrent_auslastung,MATCH(P11,bpx_kontokorrent_auslastung,1))+(P11-INDEX(bpx_kontokorrent_auslastung,MATCH(P11,bpx_kontokorrent_auslastung,1)))/(INDEX(bpx_kontokorrent_auslastung,MATCH(P11,bpx_kontokorrent_auslastung,1)+1)-INDEX(bpx_kontokorrent_auslastung,MATCH(P11,bpx_kontokorrent_auslastung,1)))*(INDEX(bpy_kontokorrent_auslastung,MATCH(P11,bpx_kontokorrent_auslastung,1)+1)-INDEX(bpy_kontokorrent_auslastung,MATCH(P11,bpx_kontokorrent_auslastung,1)))))) | R11: =IF(ISNUMBER(Q11),$B11*Q11,0) | S11: =IF(Kennzahlen!H51="","",Kennzahlen!H51) | T11: =IF(NOT(ISNUMBER(S11)),"",IF(S11<=INDEX(bpx_kontokorrent_auslastung,1),INDEX(bpy_kontokorrent_auslastung,1),IF(S11>=INDEX(bpx_kontokorrent_auslastung,COUNT(bpx_kontokorrent_auslastung)),INDEX(bpy_kontokorrent_auslastung,COUNT(bpx_kontokorrent_auslastung)),INDEX(bpy_kontokorrent_auslastung,MATCH(S11,bpx_kontokorrent_auslastung,1))+(S11-INDEX(bpx_kontokorrent_auslastung,MATCH(S11,bpx_kontokorrent_auslastung,1)))/(INDEX(bpx_kontokorrent_auslastung,MATCH(S11,bpx_kontokorrent_auslastung,1)+1)-INDEX(bpx_kontokorrent_auslastung,MATCH(S11,bpx_kontokorrent_auslastung,1)))*(INDEX(bpy_kontokorrent_auslastung,MATCH(S11,bpx_kontokorrent_auslastung,1)+1)-INDEX(bpy_kontokorrent_auslastung,MATCH(S11,bpx_kontokorrent_auslastung,1)))))) | U11: =IF(ISNUMBER(T11),$B11*T11,0) | V11: =IF(Kennzahlen!I51="","",Kennzahlen!I51) | W11: =IF(NOT(ISNUMBER(V11)),"",IF(V11<=INDEX(bpx_kontokorrent_auslastung,1),INDEX(bpy_kontokorrent_auslastung,1),IF(V11>=INDEX(bpx_kontokorrent_auslastung,COUNT(bpx_kontokorrent_auslastung)),INDEX(bpy_kontokorrent_auslastung,COUNT(bpx_kontokorrent_auslastung)),INDEX(bpy_kontokorrent_auslastung,MATCH(V11,bpx_kontokorrent_auslastung,1))+(V11-INDEX(bpx_kontokorrent_auslastung,MATCH(V11,bpx_kontokorrent_auslastung,1)))/(INDEX(bpx_kontokorrent_auslastung,MATCH(V11,bpx_kontokorrent_auslastung,1)+1)-INDEX(bpx_kontokorrent_auslastung,MATCH(V11,bpx_kontokorrent_auslastung,1)))*(INDEX(bpy_kontokorrent_auslastung,MATCH(V11,bpx_kontokorrent_auslastung,1)+1)-INDEX(bpy_kontokorrent_auslastung,MATCH(V11,bpx_kontokorrent_auslastung,1)))))) | X11: =IF(ISNUMBER(W11),$B11*W11,0)
A12: Aktualitaet der BWA | B12: 0.05 | C12: months | D12: =IF(Eingaben!C59="","",Eingaben!C59) | E12: =IF(NOT(ISNUMBER(D12)),"",IF(D12<=INDEX(bpx_bwa_age_months,1),INDEX(bpy_bwa_age_months,1),IF(D12>=INDEX(bpx_bwa_age_months,COUNT(bpx_bwa_age_months)),INDEX(bpy_bwa_age_months,COUNT(bpx_bwa_age_months)),INDEX(bpy_bwa_age_months,MATCH(D12,bpx_bwa_age_months,1))+(D12-INDEX(bpx_bwa_age_months,MATCH(D12,bpx_bwa_age_months,1)))/(INDEX(bpx_bwa_age_months,MATCH(D12,bpx_bwa_age_months,1)+1)-INDEX(bpx_bwa_age_months,MATCH(D12,bpx_bwa_age_months,1)))*(INDEX(bpy_bwa_age_months,MATCH(D12,bpx_bwa_age_months,1)+1)-INDEX(bpy_bwa_age_months,MATCH(D12,bpx_bwa_age_months,1)))))) | F12: =IF(ISNUMBER(E12),$B12*E12,0) | G12: =IF(Eingaben!D59="","",Eingaben!D59) | H12: =IF(NOT(ISNUMBER(G12)),"",IF(G12<=INDEX(bpx_bwa_age_months,1),INDEX(bpy_bwa_age_months,1),IF(G12>=INDEX(bpx_bwa_age_months,COUNT(bpx_bwa_age_months)),INDEX(bpy_bwa_age_months,COUNT(bpx_bwa_age_months)),INDEX(bpy_bwa_age_months,MATCH(G12,bpx_bwa_age_months,1))+(G12-INDEX(bpx_bwa_age_months,MATCH(G12,bpx_bwa_age_months,1)))/(INDEX(bpx_bwa_age_months,MATCH(G12,bpx_bwa_age_months,1)+1)-INDEX(bpx_bwa_age_months,MATCH(G12,bpx_bwa_age_months,1)))*(INDEX(bpy_bwa_age_months,MATCH(G12,bpx_bwa_age_months,1)+1)-INDEX(bpy_bwa_age_months,MATCH(G12,bpx_bwa_age_months,1)))))) | I12: =IF(ISNUMBER(H12),$B12*H12,0) | J12: =IF(Eingaben!E59="","",Eingaben!E59) | K12: =IF(NOT(ISNUMBER(J12)),"",IF(J12<=INDEX(bpx_bwa_age_months,1),INDEX(bpy_bwa_age_months,1),IF(J12>=INDEX(bpx_bwa_age_months,COUNT(bpx_bwa_age_months)),INDEX(bpy_bwa_age_months,COUNT(bpx_bwa_age_months)),INDEX(bpy_bwa_age_months,MATCH(J12,bpx_bwa_age_months,1))+(J12-INDEX(bpx_bwa_age_months,MATCH(J12,bpx_bwa_age_months,1)))/(INDEX(bpx_bwa_age_months,MATCH(J12,bpx_bwa_age_months,1)+1)-INDEX(bpx_bwa_age_months,MATCH(J12,bpx_bwa_age_months,1)))*(INDEX(bpy_bwa_age_months,MATCH(J12,bpx_bwa_age_months,1)+1)-INDEX(bpy_bwa_age_months,MATCH(J12,bpx_bwa_age_months,1)))))) | L12: =IF(ISNUMBER(K12),$B12*K12,0) | M12: =IF(Eingaben!F59="","",Eingaben!F59) | N12: =IF(NOT(ISNUMBER(M12)),"",IF(M12<=INDEX(bpx_bwa_age_months,1),INDEX(bpy_bwa_age_months,1),IF(M12>=INDEX(bpx_bwa_age_months,COUNT(bpx_bwa_age_months)),INDEX(bpy_bwa_age_months,COUNT(bpx_bwa_age_months)),INDEX(bpy_bwa_age_months,MATCH(M12,bpx_bwa_age_months,1))+(M12-INDEX(bpx_bwa_age_months,MATCH(M12,bpx_bwa_age_months,1)))/(INDEX(bpx_bwa_age_months,MATCH(M12,bpx_bwa_age_months,1)+1)-INDEX(bpx_bwa_age_months,MATCH(M12,bpx_bwa_age_months,1)))*(INDEX(bpy_bwa_age_months,MATCH(M12,bpx_bwa_age_months,1)+1)-INDEX(bpy_bwa_age_months,MATCH(M12,bpx_bwa_age_months,1)))))) | O12: =IF(ISNUMBER(N12),$B12*N12,0) | P12: =IF(Eingaben!G59="","",Eingaben!G59) | Q12: =IF(NOT(ISNUMBER(P12)),"",IF(P12<=INDEX(bpx_bwa_age_months,1),INDEX(bpy_bwa_age_months,1),IF(P12>=INDEX(bpx_bwa_age_months,COUNT(bpx_bwa_age_months)),INDEX(bpy_bwa_age_months,COUNT(bpx_bwa_age_months)),INDEX(bpy_bwa_age_months,MATCH(P12,bpx_bwa_age_months,1))+(P12-INDEX(bpx_bwa_age_months,MATCH(P12,bpx_bwa_age_months,1)))/(INDEX(bpx_bwa_age_months,MATCH(P12,bpx_bwa_age_months,1)+1)-INDEX(bpx_bwa_age_months,MATCH(P12,bpx_bwa_age_months,1)))*(INDEX(bpy_bwa_age_months,MATCH(P12,bpx_bwa_age_months,1)+1)-INDEX(bpy_bwa_age_months,MATCH(P12,bpx_bwa_age_months,1)))))) | R12: =IF(ISNUMBER(Q12),$B12*Q12,0) | S12: =IF(Eingaben!H59="","",Eingaben!H59) | T12: =IF(NOT(ISNUMBER(S12)),"",IF(S12<=INDEX(bpx_bwa_age_months,1),INDEX(bpy_bwa_age_months,1),IF(S12>=INDEX(bpx_bwa_age_months,COUNT(bpx_bwa_age_months)),INDEX(bpy_bwa_age_months,COUNT(bpx_bwa_age_months)),INDEX(bpy_bwa_age_months,MATCH(S12,bpx_bwa_age_months,1))+(S12-INDEX(bpx_bwa_age_months,MATCH(S12,bpx_bwa_age_months,1)))/(INDEX(bpx_bwa_age_months,MATCH(S12,bpx_bwa_age_months,1)+1)-INDEX(bpx_bwa_age_months,MATCH(S12,bpx_bwa_age_months,1)))*(INDEX(bpy_bwa_age_months,MATCH(S12,bpx_bwa_age_months,1)+1)-INDEX(bpy_bwa_age_months,MATCH(S12,bpx_bwa_age_months,1)))))) | U12: =IF(ISNUMBER(T12),$B12*T12,0) | V12: =IF(Eingaben!I59="","",Eingaben!I59) | W12: =IF(NOT(ISNUMBER(V12)),"",IF(V12<=INDEX(bpx_bwa_age_months,1),INDEX(bpy_bwa_age_months,1),IF(V12>=INDEX(bpx_bwa_age_months,COUNT(bpx_bwa_age_months)),INDEX(bpy_bwa_age_months,COUNT(bpx_bwa_age_months)),INDEX(bpy_bwa_age_months,MATCH(V12,bpx_bwa_age_months,1))+(V12-INDEX(bpx_bwa_age_months,MATCH(V12,bpx_bwa_age_months,1)))/(INDEX(bpx_bwa_age_months,MATCH(V12,bpx_bwa_age_months,1)+1)-INDEX(bpx_bwa_age_months,MATCH(V12,bpx_bwa_age_months,1)))*(INDEX(bpy_bwa_age_months,MATCH(V12,bpx_bwa_age_months,1)+1)-INDEX(bpy_bwa_age_months,MATCH(V12,bpx_bwa_age_months,1)))))) | X12: =IF(ISNUMBER(W12),$B12*W12,0)
A13: Creditreform Bonitaetsindex | B13: 0.05 | C13: index | D13: =IF(Eingaben!C60="","",Eingaben!C60) | E13: =IF(NOT(ISNUMBER(D13)),"",IF(D13<=INDEX(bpx_creditreform_bonitaetsindex,1),INDEX(bpy_creditreform_bonitaetsindex,1),IF(D13>=INDEX(bpx_creditreform_bonitaetsindex,COUNT(bpx_creditreform_bonitaetsindex)),INDEX(bpy_creditreform_bonitaetsindex,COUNT(bpx_creditreform_bonitaetsindex)),INDEX(bpy_creditreform_bonitaetsindex,MATCH(D13,bpx_creditreform_bonitaetsindex,1))+(D13-INDEX(bpx_creditreform_bonitaetsindex,MATCH(D13,bpx_creditreform_bonitaetsindex,1)))/(INDEX(bpx_creditreform_bonitaetsindex,MATCH(D13,bpx_creditreform_bonitaetsindex,1)+1)-INDEX(bpx_creditreform_bonitaetsindex,MATCH(D13,bpx_creditreform_bonitaetsindex,1)))*(INDEX(bpy_creditreform_bonitaetsindex,MATCH(D13,bpx_creditreform_bonitaetsindex,1)+1)-INDEX(bpy_creditreform_bonitaetsindex,MATCH(D13,bpx_creditreform_bonitaetsindex,1)))))) | F13: =IF(ISNUMBER(E13),$B13*E13,0) | G13: =IF(Eingaben!D60="","",Eingaben!D60) | H13: =IF(NOT(ISNUMBER(G13)),"",IF(G13<=INDEX(bpx_creditreform_bonitaetsindex,1),INDEX(bpy_creditreform_bonitaetsindex,1),IF(G13>=INDEX(bpx_creditreform_bonitaetsindex,COUNT(bpx_creditreform_bonitaetsindex)),INDEX(bpy_creditreform_bonitaetsindex,COUNT(bpx_creditreform_bonitaetsindex)),INDEX(bpy_creditreform_bonitaetsindex,MATCH(G13,bpx_creditreform_bonitaetsindex,1))+(G13-INDEX(bpx_creditreform_bonitaetsindex,MATCH(G13,bpx_creditreform_bonitaetsindex,1)))/(INDEX(bpx_creditreform_bonitaetsindex,MATCH(G13,bpx_creditreform_bonitaetsindex,1)+1)-INDEX(bpx_creditreform_bonitaetsindex,MATCH(G13,bpx_creditreform_bonitaetsindex,1)))*(INDEX(bpy_creditreform_bonitaetsindex,MATCH(G13,bpx_creditreform_bonitaetsindex,1)+1)-INDEX(bpy_creditreform_bonitaetsindex,MATCH(G13,bpx_creditreform_bonitaetsindex,1)))))) | I13: =IF(ISNUMBER(H13),$B13*H13,0) | J13: =IF(Eingaben!E60="","",Eingaben!E60) | K13: =IF(NOT(ISNUMBER(J13)),"",IF(J13<=INDEX(bpx_creditreform_bonitaetsindex,1),INDEX(bpy_creditreform_bonitaetsindex,1),IF(J13>=INDEX(bpx_creditreform_bonitaetsindex,COUNT(bpx_creditreform_bonitaetsindex)),INDEX(bpy_creditreform_bonitaetsindex,COUNT(bpx_creditreform_bonitaetsindex)),INDEX(bpy_creditreform_bonitaetsindex,MATCH(J13,bpx_creditreform_bonitaetsindex,1))+(J13-INDEX(bpx_creditreform_bonitaetsindex,MATCH(J13,bpx_creditreform_bonitaetsindex,1)))/(INDEX(bpx_creditreform_bonitaetsindex,MATCH(J13,bpx_creditreform_bonitaetsindex,1)+1)-INDEX(bpx_creditreform_bonitaetsindex,MATCH(J13,bpx_creditreform_bonitaetsindex,1)))*(INDEX(bpy_creditreform_bonitaetsindex,MATCH(J13,bpx_creditreform_bonitaetsindex,1)+1)-INDEX(bpy_creditreform_bonitaetsindex,MATCH(J13,bpx_creditreform_bonitaetsindex,1)))))) | L13: =IF(ISNUMBER(K13),$B13*K13,0) | M13: =IF(Eingaben!F60="","",Eingaben!F60) | N13: =IF(NOT(ISNUMBER(M13)),"",IF(M13<=INDEX(bpx_creditreform_bonitaetsindex,1),INDEX(bpy_creditreform_bonitaetsindex,1),IF(M13>=INDEX(bpx_creditreform_bonitaetsindex,COUNT(bpx_creditreform_bonitaetsindex)),INDEX(bpy_creditreform_bonitaetsindex,COUNT(bpx_creditreform_bonitaetsindex)),INDEX(bpy_creditreform_bonitaetsindex,MATCH(M13,bpx_creditreform_bonitaetsindex,1))+(M13-INDEX(bpx_creditreform_bonitaetsindex,MATCH(M13,bpx_creditreform_bonitaetsindex,1)))/(INDEX(bpx_creditreform_bonitaetsindex,MATCH(M13,bpx_creditreform_bonitaetsindex,1)+1)-INDEX(bpx_creditreform_bonitaetsindex,MATCH(M13,bpx_creditreform_bonitaetsindex,1)))*(INDEX(bpy_creditreform_bonitaetsindex,MATCH(M13,bpx_creditreform_bonitaetsindex,1)+1)-INDEX(bpy_creditreform_bonitaetsindex,MATCH(M13,bpx_creditreform_bonitaetsindex,1)))))) | O13: =IF(ISNUMBER(N13),$B13*N13,0) | P13: =IF(Eingaben!G60="","",Eingaben!G60) | Q13: =IF(NOT(ISNUMBER(P13)),"",IF(P13<=INDEX(bpx_creditreform_bonitaetsindex,1),INDEX(bpy_creditreform_bonitaetsindex,1),IF(P13>=INDEX(bpx_creditreform_bonitaetsindex,COUNT(bpx_creditreform_bonitaetsindex)),INDEX(bpy_creditreform_bonitaetsindex,COUNT(bpx_creditreform_bonitaetsindex)),INDEX(bpy_creditreform_bonitaetsindex,MATCH(P13,bpx_creditreform_bonitaetsindex,1))+(P13-INDEX(bpx_creditreform_bonitaetsindex,MATCH(P13,bpx_creditreform_bonitaetsindex,1)))/(INDEX(bpx_creditreform_bonitaetsindex,MATCH(P13,bpx_creditreform_bonitaetsindex,1)+1)-INDEX(bpx_creditreform_bonitaetsindex,MATCH(P13,bpx_creditreform_bonitaetsindex,1)))*(INDEX(bpy_creditreform_bonitaetsindex,MATCH(P13,bpx_creditreform_bonitaetsindex,1)+1)-INDEX(bpy_creditreform_bonitaetsindex,MATCH(P13,bpx_creditreform_bonitaetsindex,1)))))) | R13: =IF(ISNUMBER(Q13),$B13*Q13,0) | S13: =IF(Eingaben!H60="","",Eingaben!H60) | T13: =IF(NOT(ISNUMBER(S13)),"",IF(S13<=INDEX(bpx_creditreform_bonitaetsindex,1),INDEX(bpy_creditreform_bonitaetsindex,1),IF(S13>=INDEX(bpx_creditreform_bonitaetsindex,COUNT(bpx_creditreform_bonitaetsindex)),INDEX(bpy_creditreform_bonitaetsindex,COUNT(bpx_creditreform_bonitaetsindex)),INDEX(bpy_creditreform_bonitaetsindex,MATCH(S13,bpx_creditreform_bonitaetsindex,1))+(S13-INDEX(bpx_creditreform_bonitaetsindex,MATCH(S13,bpx_creditreform_bonitaetsindex,1)))/(INDEX(bpx_creditreform_bonitaetsindex,MATCH(S13,bpx_creditreform_bonitaetsindex,1)+1)-INDEX(bpx_creditreform_bonitaetsindex,MATCH(S13,bpx_creditreform_bonitaetsindex,1)))*(INDEX(bpy_creditreform_bonitaetsindex,MATCH(S13,bpx_creditreform_bonitaetsindex,1)+1)-INDEX(bpy_creditreform_bonitaetsindex,MATCH(S13,bpx_creditreform_bonitaetsindex,1)))))) | U13: =IF(ISNUMBER(T13),$B13*T13,0) | V13: =IF(Eingaben!I60="","",Eingaben!I60) | W13: =IF(NOT(ISNUMBER(V13)),"",IF(V13<=INDEX(bpx_creditreform_bonitaetsindex,1),INDEX(bpy_creditreform_bonitaetsindex,1),IF(V13>=INDEX(bpx_creditreform_bonitaetsindex,COUNT(bpx_creditreform_bonitaetsindex)),INDEX(bpy_creditreform_bonitaetsindex,COUNT(bpx_creditreform_bonitaetsindex)),INDEX(bpy_creditreform_bonitaetsindex,MATCH(V13,bpx_creditreform_bonitaetsindex,1))+(V13-INDEX(bpx_creditreform_bonitaetsindex,MATCH(V13,bpx_creditreform_bonitaetsindex,1)))/(INDEX(bpx_creditreform_bonitaetsindex,MATCH(V13,bpx_creditreform_bonitaetsindex,1)+1)-INDEX(bpx_creditreform_bonitaetsindex,MATCH(V13,bpx_creditreform_bonitaetsindex,1)))*(INDEX(bpy_creditreform_bonitaetsindex,MATCH(V13,bpx_creditreform_bonitaetsindex,1)+1)-INDEX(bpy_creditreform_bonitaetsindex,MATCH(V13,bpx_creditreform_bonitaetsindex,1)))))) | X13: =IF(ISNUMBER(W13),$B13*W13,0)
A14: Zahlungsverhalten | B14: 0.04 | C14: index | D14: =IF(Kennzahlen!C52="","",Kennzahlen!C52) | E14: =IF(NOT(ISNUMBER(D14)),"",IF(D14<=INDEX(bpx_zahlungsverhalten,1),INDEX(bpy_zahlungsverhalten,1),IF(D14>=INDEX(bpx_zahlungsverhalten,COUNT(bpx_zahlungsverhalten)),INDEX(bpy_zahlungsverhalten,COUNT(bpx_zahlungsverhalten)),INDEX(bpy_zahlungsverhalten,MATCH(D14,bpx_zahlungsverhalten,1))+(D14-INDEX(bpx_zahlungsverhalten,MATCH(D14,bpx_zahlungsverhalten,1)))/(INDEX(bpx_zahlungsverhalten,MATCH(D14,bpx_zahlungsverhalten,1)+1)-INDEX(bpx_zahlungsverhalten,MATCH(D14,bpx_zahlungsverhalten,1)))*(INDEX(bpy_zahlungsverhalten,MATCH(D14,bpx_zahlungsverhalten,1)+1)-INDEX(bpy_zahlungsverhalten,MATCH(D14,bpx_zahlungsverhalten,1)))))) | F14: =IF(ISNUMBER(E14),$B14*E14,0) | G14: =IF(Kennzahlen!D52="","",Kennzahlen!D52) | H14: =IF(NOT(ISNUMBER(G14)),"",IF(G14<=INDEX(bpx_zahlungsverhalten,1),INDEX(bpy_zahlungsverhalten,1),IF(G14>=INDEX(bpx_zahlungsverhalten,COUNT(bpx_zahlungsverhalten)),INDEX(bpy_zahlungsverhalten,COUNT(bpx_zahlungsverhalten)),INDEX(bpy_zahlungsverhalten,MATCH(G14,bpx_zahlungsverhalten,1))+(G14-INDEX(bpx_zahlungsverhalten,MATCH(G14,bpx_zahlungsverhalten,1)))/(INDEX(bpx_zahlungsverhalten,MATCH(G14,bpx_zahlungsverhalten,1)+1)-INDEX(bpx_zahlungsverhalten,MATCH(G14,bpx_zahlungsverhalten,1)))*(INDEX(bpy_zahlungsverhalten,MATCH(G14,bpx_zahlungsverhalten,1)+1)-INDEX(bpy_zahlungsverhalten,MATCH(G14,bpx_zahlungsverhalten,1)))))) | I14: =IF(ISNUMBER(H14),$B14*H14,0) | J14: =IF(Kennzahlen!E52="","",Kennzahlen!E52) | K14: =IF(NOT(ISNUMBER(J14)),"",IF(J14<=INDEX(bpx_zahlungsverhalten,1),INDEX(bpy_zahlungsverhalten,1),IF(J14>=INDEX(bpx_zahlungsverhalten,COUNT(bpx_zahlungsverhalten)),INDEX(bpy_zahlungsverhalten,COUNT(bpx_zahlungsverhalten)),INDEX(bpy_zahlungsverhalten,MATCH(J14,bpx_zahlungsverhalten,1))+(J14-INDEX(bpx_zahlungsverhalten,MATCH(J14,bpx_zahlungsverhalten,1)))/(INDEX(bpx_zahlungsverhalten,MATCH(J14,bpx_zahlungsverhalten,1)+1)-INDEX(bpx_zahlungsverhalten,MATCH(J14,bpx_zahlungsverhalten,1)))*(INDEX(bpy_zahlungsverhalten,MATCH(J14,bpx_zahlungsverhalten,1)+1)-INDEX(bpy_zahlungsverhalten,MATCH(J14,bpx_zahlungsverhalten,1)))))) | L14: =IF(ISNUMBER(K14),$B14*K14,0) | M14: =IF(Kennzahlen!F52="","",Kennzahlen!F52) | N14: =IF(NOT(ISNUMBER(M14)),"",IF(M14<=INDEX(bpx_zahlungsverhalten,1),INDEX(bpy_zahlungsverhalten,1),IF(M14>=INDEX(bpx_zahlungsverhalten,COUNT(bpx_zahlungsverhalten)),INDEX(bpy_zahlungsverhalten,COUNT(bpx_zahlungsverhalten)),INDEX(bpy_zahlungsverhalten,MATCH(M14,bpx_zahlungsverhalten,1))+(M14-INDEX(bpx_zahlungsverhalten,MATCH(M14,bpx_zahlungsverhalten,1)))/(INDEX(bpx_zahlungsverhalten,MATCH(M14,bpx_zahlungsverhalten,1)+1)-INDEX(bpx_zahlungsverhalten,MATCH(M14,bpx_zahlungsverhalten,1)))*(INDEX(bpy_zahlungsverhalten,MATCH(M14,bpx_zahlungsverhalten,1)+1)-INDEX(bpy_zahlungsverhalten,MATCH(M14,bpx_zahlungsverhalten,1)))))) | O14: =IF(ISNUMBER(N14),$B14*N14,0) | P14: =IF(Kennzahlen!G52="","",Kennzahlen!G52) | Q14: =IF(NOT(ISNUMBER(P14)),"",IF(P14<=INDEX(bpx_zahlungsverhalten,1),INDEX(bpy_zahlungsverhalten,1),IF(P14>=INDEX(bpx_zahlungsverhalten,COUNT(bpx_zahlungsverhalten)),INDEX(bpy_zahlungsverhalten,COUNT(bpx_zahlungsverhalten)),INDEX(bpy_zahlungsverhalten,MATCH(P14,bpx_zahlungsverhalten,1))+(P14-INDEX(bpx_zahlungsverhalten,MATCH(P14,bpx_zahlungsverhalten,1)))/(INDEX(bpx_zahlungsverhalten,MATCH(P14,bpx_zahlungsverhalten,1)+1)-INDEX(bpx_zahlungsverhalten,MATCH(P14,bpx_zahlungsverhalten,1)))*(INDEX(bpy_zahlungsverhalten,MATCH(P14,bpx_zahlungsverhalten,1)+1)-INDEX(bpy_zahlungsverhalten,MATCH(P14,bpx_zahlungsverhalten,1)))))) | R14: =IF(ISNUMBER(Q14),$B14*Q14,0) | S14: =IF(Kennzahlen!H52="","",Kennzahlen!H52) | T14: =IF(NOT(ISNUMBER(S14)),"",IF(S14<=INDEX(bpx_zahlungsverhalten,1),INDEX(bpy_zahlungsverhalten,1),IF(S14>=INDEX(bpx_zahlungsverhalten,COUNT(bpx_zahlungsverhalten)),INDEX(bpy_zahlungsverhalten,COUNT(bpx_zahlungsverhalten)),INDEX(bpy_zahlungsverhalten,MATCH(S14,bpx_zahlungsverhalten,1))+(S14-INDEX(bpx_zahlungsverhalten,MATCH(S14,bpx_zahlungsverhalten,1)))/(INDEX(bpx_zahlungsverhalten,MATCH(S14,bpx_zahlungsverhalten,1)+1)-INDEX(bpx_zahlungsverhalten,MATCH(S14,bpx_zahlungsverhalten,1)))*(INDEX(bpy_zahlungsverhalten,MATCH(S14,bpx_zahlungsverhalten,1)+1)-INDEX(bpy_zahlungsverhalten,MATCH(S14,bpx_zahlungsverhalten,1)))))) | U14: =IF(ISNUMBER(T14),$B14*T14,0) | V14: =IF(Kennzahlen!I52="","",Kennzahlen!I52) | W14: =IF(NOT(ISNUMBER(V14)),"",IF(V14<=INDEX(bpx_zahlungsverhalten,1),INDEX(bpy_zahlungsverhalten,1),IF(V14>=INDEX(bpx_zahlungsverhalten,COUNT(bpx_zahlungsverhalten)),INDEX(bpy_zahlungsverhalten,COUNT(bpx_zahlungsverhalten)),INDEX(bpy_zahlungsverhalten,MATCH(V14,bpx_zahlungsverhalten,1))+(V14-INDEX(bpx_zahlungsverhalten,MATCH(V14,bpx_zahlungsverhalten,1)))/(INDEX(bpx_zahlungsverhalten,MATCH(V14,bpx_zahlungsverhalten,1)+1)-INDEX(bpx_zahlungsverhalten,MATCH(V14,bpx_zahlungsverhalten,1)))*(INDEX(bpy_zahlungsverhalten,MATCH(V14,bpx_zahlungsverhalten,1)+1)-INDEX(bpy_zahlungsverhalten,MATCH(V14,bpx_zahlungsverhalten,1)))))) | X14: =IF(ISNUMBER(W14),$B14*W14,0)
A16: Summe der Gewichte mit Punkten | D16: =SUMPRODUCT(($B$5:$B$14)*ISNUMBER(E5:E14)) | G16: =SUMPRODUCT(($B$5:$B$14)*ISNUMBER(H5:H14)) | J16: =SUMPRODUCT(($B$5:$B$14)*ISNUMBER(K5:K14)) | M16: =SUMPRODUCT(($B$5:$B$14)*ISNUMBER(N5:N14)) | P16: =SUMPRODUCT(($B$5:$B$14)*ISNUMBER(Q5:Q14)) | S16: =SUMPRODUCT(($B$5:$B$14)*ISNUMBER(T5:T14)) | V16: =SUMPRODUCT(($B$5:$B$14)*ISNUMBER(W5:W14))
A17: Abdeckung (Coverage) | D17: =D16 | G17: =G16 | J17: =J16 | M17: =M16 | P17: =P16 | S17: =S16 | V17: =V16
A18: Summe Gewicht x Punkte | D18: =SUM(F5:F14) | G18: =SUM(I5:I14) | J18: =SUM(L5:L14) | M18: =SUM(O5:O14) | P18: =SUM(R5:R14) | S18: =SUM(U5:U14) | V18: =SUM(X5:X14)
A19: Gesamtscore (renormiert) | D19: =IF(D16=0,0,D18/D16) | G19: =IF(G16=0,0,G18/G16) | J19: =IF(J16=0,0,J18/J16) | M19: =IF(M16=0,0,M18/M16) | P19: =IF(P16=0,0,P18/P16) | S19: =IF(S16=0,0,S18/S16) | V19: =IF(V16=0,0,V18/V16)
A20: Readiness-Band | D20: =IF(D19>=78.0,"A",IF(D19>=65.0,"B",IF(D19>=52.0,"C",IF(D19>=38.0,"D","E")))) | G20: =IF(G19>=78.0,"A",IF(G19>=65.0,"B",IF(G19>=52.0,"C",IF(G19>=38.0,"D","E")))) | J20: =IF(J19>=78.0,"A",IF(J19>=65.0,"B",IF(J19>=52.0,"C",IF(J19>=38.0,"D","E")))) | M20: =IF(M19>=78.0,"A",IF(M19>=65.0,"B",IF(M19>=52.0,"C",IF(M19>=38.0,"D","E")))) | P20: =IF(P19>=78.0,"A",IF(P19>=65.0,"B",IF(P19>=52.0,"C",IF(P19>=38.0,"D","E")))) | S20: =IF(S19>=78.0,"A",IF(S19>=65.0,"B",IF(S19>=52.0,"C",IF(S19>=38.0,"D","E")))) | V20: =IF(V19>=78.0,"A",IF(V19>=65.0,"B",IF(V19>=52.0,"C",IF(V19>=38.0,"D","E"))))
A21: Engine-Score (Referenz) | G21: 66.4 | J21: 50.7 | M21: 4.2 | P21: 90.7 | S21: 72.1 | V21: 93.3
A22: Engine-Band (Referenz) | G22: B | J22: D | M22: E | P22: A | S22: B | V22: A
A23: Differenz Excel - Engine | D23: =IF(NOT(ISNUMBER(D21)),"",ROUND(D19,1)-D21) | G23: =IF(NOT(ISNUMBER(G21)),"",ROUND(G19,1)-G21) | J23: =IF(NOT(ISNUMBER(J21)),"",ROUND(J19,1)-J21) | M23: =IF(NOT(ISNUMBER(M21)),"",ROUND(M19,1)-M21) | P23: =IF(NOT(ISNUMBER(P21)),"",ROUND(P19,1)-P21) | S23: =IF(NOT(ISNUMBER(S21)),"",ROUND(S19,1)-S21) | V23: =IF(NOT(ISNUMBER(V21)),"",ROUND(V19,1)-V21)
A24: Status | D24: =IF(D23="","eigener Fall",IF(ABS(D23)<=0.05,"OK","ABWEICHUNG")) | G24: =IF(G23="","eigener Fall",IF(ABS(G23)<=0.05,"OK","ABWEICHUNG")) | J24: =IF(J23="","eigener Fall",IF(ABS(J23)<=0.05,"OK","ABWEICHUNG")) | M24: =IF(M23="","eigener Fall",IF(ABS(M23)<=0.05,"OK","ABWEICHUNG")) | P24: =IF(P23="","eigener Fall",IF(ABS(P23)<=0.05,"OK","ABWEICHUNG")) | S24: =IF(S23="","eigener Fall",IF(ABS(S23)<=0.05,"OK","ABWEICHUNG")) | V24: =IF(V23="","eigener Fall",IF(ABS(V23)<=0.05,"OK","ABWEICHUNG"))

Sheet Abgleich
A1: Abgleich Excel gegen Engine / reconciliation
A2: Punkte je Faktor. Alles ausser 'OK' bedeutet: eine der beiden Seiten rechnet falsch.
A4: Faktor | B4: Mueller Praezisionstechnik GmbH | C4: Nordlicht Handel GmbH & Co. KG | D4: Gastro Rheinblick GmbH | E4: Datenwerk Consulting GmbH | F4: Ihrig Sanitaer- und Heizungstechnik GmbH | G4: Hoffmann Medizintechnik GmbH
A5: Eigenkapitalquote (wirtschaftlich) | B5: =IF(NOT(ISNUMBER(Scorecard!H5)),"ABWEICHUNG: Excel wertet nicht",IF(ABS(Scorecard!H5-48.50659716566216)<=0.05,"OK","ABWEICHUNG "&TEXT(Scorecard!H5-48.50659716566216,"0.00"))) | C5: =IF(NOT(ISNUMBER(Scorecard!K5)),"ABWEICHUNG: Excel wertet nicht",IF(ABS(Scorecard!K5-50.491203377902885)<=0.05,"OK","ABWEICHUNG "&TEXT(Scorecard!K5-50.491203377902885,"0.00"))) | D5: =IF(NOT(ISNUMBER(Scorecard!N5)),"ABWEICHUNG: Excel wertet nicht",IF(ABS(Scorecard!N5-0.0)<=0.05,"OK","ABWEICHUNG "&TEXT(Scorecard!N5-0.0,"0.00"))) | E5: =IF(NOT(ISNUMBER(Scorecard!Q5)),"ABWEICHUNG: Excel wertet nicht",IF(ABS(Scorecard!Q5-79.10054296948137)<=0.05,"OK","ABWEICHUNG "&TEXT(Scorecard!Q5-79.10054296948137,"0.00"))) | F5: =IF(NOT(ISNUMBER(Scorecard!T5)),"ABWEICHUNG: Excel wertet nicht",IF(ABS(Scorecard!T5-63.329906475333765)<=0.05,"OK","ABWEICHUNG "&TEXT(Scorecard!T5-63.329906475333765,"0.00"))) | G5: =IF(NOT(ISNUMBER(Scorecard!W5)),"ABWEICHUNG: Excel wertet nicht",IF(ABS(Scorecard!W5-84.86024431444758)<=0.05,"OK","ABWEICHUNG "&TEXT(Scorecard!W5-84.86024431444758,"0.00")))
A6: Kapitaldienstfaehigkeit inkl. neuer Finanzierung (DSCR) | B6: =IF(NOT(ISNUMBER(Scorecard!H6)),"ABWEICHUNG: Excel wertet nicht",IF(ABS(Scorecard!H6-88.00156733688883)<=0.05,"OK","ABWEICHUNG "&TEXT(Scorecard!H6-88.00156733688883,"0.00"))) | C6: =IF(NOT(ISNUMBER(Scorecard!K6)),"ABWEICHUNG: Excel wertet nicht",IF(ABS(Scorecard!K6-41.25650471620631)<=0.05,"OK","ABWEICHUNG "&TEXT(Scorecard!K6-41.25650471620631,"0.00"))) | D6: =IF(NOT(ISNUMBER(Scorecard!N6)),"ABWEICHUNG: Excel wertet nicht",IF(ABS(Scorecard!N6-0.0)<=0.05,"OK","ABWEICHUNG "&TEXT(Scorecard!N6-0.0,"0.00"))) | E6: =IF(NOT(ISNUMBER(Scorecard!Q6)),"ABWEICHUNG: Excel wertet nicht",IF(ABS(Scorecard!Q6-100.0)<=0.05,"OK","ABWEICHUNG "&TEXT(Scorecard!Q6-100.0,"0.00"))) | F6: =IF(NOT(ISNUMBER(Scorecard!T6)),"ABWEICHUNG: Excel wertet nicht",IF(ABS(Scorecard!T6-80.02917851512724)<=0.05,"OK","ABWEICHUNG "&TEXT(Scorecard!T6-80.02917851512724,"0.00"))) | G6: =IF(NOT(ISNUMBER(Scorecard!W6)),"ABWEICHUNG: Excel wertet nicht",IF(ABS(Scorecard!W6-100.0)<=0.05,"OK","ABWEICHUNG "&TEXT(Scorecard!W6-100.0,"0.00")))
A7: Dynamischer Verschuldungsgrad (Nettoverschuldung / EBITDA) | B7: =IF(NOT(ISNUMBER(Scorecard!H7)),"ABWEICHUNG: Excel wertet nicht",IF(ABS(Scorecard!H7-68.12)<=0.05,"OK","ABWEICHUNG "&TEXT(Scorecard!H7-68.12,"0.00"))) | C7: =IF(NOT(ISNUMBER(Scorecard!K7)),"ABWEICHUNG: Excel wertet nicht",IF(ABS(Scorecard!K7-47.15384615384615)<=0.05,"OK","ABWEICHUNG "&TEXT(Scorecard!K7-47.15384615384615,"0.00"))) | D7: =IF(NOT(ISNUMBER(Scorecard!N7)),"ABWEICHUNG: Excel wertet nicht",IF(ABS(Scorecard!N7-0.0)<=0.05,"OK","ABWEICHUNG "&TEXT(Scorecard!N7-0.0,"0.00"))) | E7: =IF(NOT(ISNUMBER(Scorecard!Q7)),"ABWEICHUNG: Excel wertet nicht",IF(ABS(Scorecard!Q7-100.0)<=0.05,"OK","ABWEICHUNG "&TEXT(Scorecard!Q7-100.0,"0.00"))) | F7: =IF(NOT(ISNUMBER(Scorecard!T7)),"ABWEICHUNG: Excel wertet nicht",IF(ABS(Scorecard!T7-79.67999999999999)<=0.05,"OK","ABWEICHUNG "&TEXT(Scorecard!T7-79.67999999999999,"0.00"))) | G7: =IF(NOT(ISNUMBER(Scorecard!W7)),"ABWEICHUNG: Excel wertet nicht",IF(ABS(Scorecard!W7-100.0)<=0.05,"OK","ABWEICHUNG "&TEXT(Scorecard!W7-100.0,"0.00")))
A8: EBIT-Marge | B8: =IF(NOT(ISNUMBER(Scorecard!H8)),"ABWEICHUNG: Excel wertet nicht",IF(ABS(Scorecard!H8-69.59110473457676)<=0.05,"OK","ABWEICHUNG "&TEXT(Scorecard!H8-69.59110473457676,"0.00"))) | C8: =IF(NOT(ISNUMBER(Scorecard!K8)),"ABWEICHUNG: Excel wertet nicht",IF(ABS(Scorecard!K8-62.368421052631575)<=0.05,"OK","ABWEICHUNG "&TEXT(Scorecard!K8-62.368421052631575,"0.00"))) | D8: =IF(NOT(ISNUMBER(Scorecard!N8)),"ABWEICHUNG: Excel wertet nicht",IF(ABS(Scorecard!N8-0.0)<=0.05,"OK","ABWEICHUNG "&TEXT(Scorecard!N8-0.0,"0.00"))) | E8: =IF(NOT(ISNUMBER(Scorecard!Q8)),"ABWEICHUNG: Excel wertet nicht",IF(ABS(Scorecard!Q8-77.99975502204802)<=0.05,"OK","ABWEICHUNG "&TEXT(Scorecard!Q8-77.99975502204802,"0.00"))) | F8: =IF(NOT(ISNUMBER(Scorecard!T8)),"ABWEICHUNG: Excel wertet nicht",IF(ABS(Scorecard!T8-68.55526826115062)<=0.05,"OK","ABWEICHUNG "&TEXT(Scorecard!T8-68.55526826115062,"0.00"))) | G8: =IF(NOT(ISNUMBER(Scorecard!W8)),"ABWEICHUNG: Excel wertet nicht",IF(ABS(Scorecard!W8-80.29768177028451)<=0.05,"OK","ABWEICHUNG "&TEXT(Scorecard!W8-80.29768177028451,"0.00")))
A9: Liquiditaet 2. Grades | B9: =IF(NOT(ISNUMBER(Scorecard!H9)),"ABWEICHUNG: Excel wertet nicht",IF(ABS(Scorecard!H9-70.7274861646822)<=0.05,"OK","ABWEICHUNG "&TEXT(Scorecard!H9-70.7274861646822,"0.00"))) | C9: =IF(NOT(ISNUMBER(Scorecard!K9)),"ABWEICHUNG: Excel wertet nicht",IF(ABS(Scorecard!K9-62.45979204289897)<=0.05,"OK","ABWEICHUNG "&TEXT(Scorecard!K9-62.45979204289897,"0.00"))) | D9: =IF(NOT(ISNUMBER(Scorecard!N9)),"ABWEICHUNG: Excel wertet nicht",IF(ABS(Scorecard!N9-7.9610266159695815)<=0.05,"OK","ABWEICHUNG "&TEXT(Scorecard!N9-7.9610266159695815,"0.00"))) | E9: =IF(NOT(ISNUMBER(Scorecard!Q9)),"ABWEICHUNG: Excel wertet nicht",IF(ABS(Scorecard!Q9-86.94036170084074)<=0.05,"OK","ABWEICHUNG "&TEXT(Scorecard!Q9-86.94036170084074,"0.00"))) | F9: =IF(NOT(ISNUMBER(Scorecard!T9)),"ABWEICHUNG: Excel wertet nicht",IF(ABS(Scorecard!T9-76.1940646157931)<=0.05,"OK","ABWEICHUNG "&TEXT(Scorecard!T9-76.1940646157931,"0.00"))) | G9: =IF(NOT(ISNUMBER(Scorecard!W9)),"ABWEICHUNG: Excel wertet nicht",IF(ABS(Scorecard!W9-89.26782798040283)<=0.05,"OK","ABWEICHUNG "&TEXT(Scorecard!W9-89.26782798040283,"0.00")))
A10: Zinsdeckungsgrad (EBIT / Zinsaufwand) | B10: =IF(NOT(ISNUMBER(Scorecard!H10)),"ABWEICHUNG: Excel wertet nicht",IF(ABS(Scorecard!H10-79.0)<=0.05,"OK","ABWEICHUNG "&TEXT(Scorecard!H10-79.0,"0.00"))) | C10: =IF(NOT(ISNUMBER(Scorecard!K10)),"ABWEICHUNG: Excel wertet nicht",IF(ABS(Scorecard!K10-49.7972972972973)<=0.05,"OK","ABWEICHUNG "&TEXT(Scorecard!K10-49.7972972972973,"0.00"))) | D10: =IF(NOT(ISNUMBER(Scorecard!N10)),"ABWEICHUNG: Excel wertet nicht",IF(ABS(Scorecard!N10-0.0)<=0.05,"OK","ABWEICHUNG "&TEXT(Scorecard!N10-0.0,"0.00"))) | E10: =IF(NOT(ISNUMBER(Scorecard!Q10)),"ABWEICHUNG: Excel wertet nicht",IF(ABS(Scorecard!Q10-100.0)<=0.05,"OK","ABWEICHUNG "&TEXT(Scorecard!Q10-100.0,"0.00"))) | F10: =IF(NOT(ISNUMBER(Scorecard!T10)),"ABWEICHUNG: Excel wertet nicht",IF(ABS(Scorecard!T10-84.82352941176471)<=0.05,"OK","ABWEICHUNG "&TEXT(Scorecard!T10-84.82352941176471,"0.00"))) | G10: =IF(NOT(ISNUMBER(Scorecard!W10)),"ABWEICHUNG: Excel wertet nicht",IF(ABS(Scorecard!W10-100.0)<=0.05,"OK","ABWEICHUNG "&TEXT(Scorecard!W10-100.0,"0.00")))
A11: Kontokorrent-Auslastung | B11: =IF(NOT(ISNUMBER(Scorecard!H11)),"ABWEICHUNG: Excel wertet nicht",IF(ABS(Scorecard!H11-38.20000000000001)<=0.05,"OK","ABWEICHUNG "&TEXT(Scorecard!H11-38.20000000000001,"0.00"))) | C11: =IF(NOT(ISNUMBER(Scorecard!K11)),"ABWEICHUNG: Excel wertet nicht",IF(ABS(Scorecard!K11-14.799999999999994)<=0.05,"OK","ABWEICHUNG "&TEXT(Scorecard!K11-14.799999999999994,"0.00"))) | D11: =IF(NOT(ISNUMBER(Scorecard!N11)),"ABWEICHUNG: Excel wertet nicht",IF(ABS(Scorecard!N11-19.00000000000001)<=0.05,"OK","ABWEICHUNG "&TEXT(Scorecard!N11-19.00000000000001,"0.00"))) | E11: =IF(NOT(ISNUMBER(Scorecard!Q11)),"ABWEICHUNG: Excel wertet nicht",IF(ABS(Scorecard!Q11-100.0)<=0.05,"OK","ABWEICHUNG "&TEXT(Scorecard!Q11-100.0,"0.00"))) | F11: =IF(NOT(ISNUMBER(Scorecard!T11)),"ABWEICHUNG: Excel wertet nicht",IF(ABS(Scorecard!T11-88.4)<=0.05,"OK","ABWEICHUNG "&TEXT(Scorecard!T11-88.4,"0.00"))) | G11: =IF(NOT(ISNUMBER(Scorecard!W11)),"ABWEICHUNG: Excel wertet nicht",IF(ABS(Scorecard!W11-100.0)<=0.05,"OK","ABWEICHUNG "&TEXT(Scorecard!W11-100.0,"0.00")))
A12: Aktualitaet der BWA | B12: =IF(NOT(ISNUMBER(Scorecard!H12)),"ABWEICHUNG: Excel wertet nicht",IF(ABS(Scorecard!H12-43.5)<=0.05,"OK","ABWEICHUNG "&TEXT(Scorecard!H12-43.5,"0.00"))) | C12: =IF(NOT(ISNUMBER(Scorecard!K12)),"ABWEICHUNG: Excel wertet nicht",IF(ABS(Scorecard!K12-90.0)<=0.05,"OK","ABWEICHUNG "&TEXT(Scorecard!K12-90.0,"0.00"))) | D12: =IF(NOT(ISNUMBER(Scorecard!N12)),"ABWEICHUNG: Excel wertet nicht",IF(ABS(Scorecard!N12-25.333333333333336)<=0.05,"OK","ABWEICHUNG "&TEXT(Scorecard!N12-25.333333333333336,"0.00"))) | E12: =IF(NOT(ISNUMBER(Scorecard!Q12)),"ABWEICHUNG: Excel wertet nicht",IF(ABS(Scorecard!Q12-90.0)<=0.05,"OK","ABWEICHUNG "&TEXT(Scorecard!Q12-90.0,"0.00"))) | F12: =IF(NOT(ISNUMBER(Scorecard!T12)),"ABWEICHUNG: Excel wertet nicht",IF(ABS(Scorecard!T12-12.0)<=0.05,"OK","ABWEICHUNG "&TEXT(Scorecard!T12-12.0,"0.00"))) | G12: =IF(NOT(ISNUMBER(Scorecard!W12)),"ABWEICHUNG: Excel wertet nicht",IF(ABS(Scorecard!W12-100.0)<=0.05,"OK","ABWEICHUNG "&TEXT(Scorecard!W12-100.0,"0.00")))
A13: Creditreform Bonitaetsindex | B13: =IF(NOT(ISNUMBER(Scorecard!H13)),"ABWEICHUNG: Excel wertet nicht",IF(ABS(Scorecard!H13-72.52)<=0.05,"OK","ABWEICHUNG "&TEXT(Scorecard!H13-72.52,"0.00"))) | C13: =IF(NOT(ISNUMBER(Scorecard!K13)),"ABWEICHUNG: Excel wertet nicht",IF(ABS(Scorecard!K13-58.74)<=0.05,"OK","ABWEICHUNG "&TEXT(Scorecard!K13-58.74,"0.00"))) | D13: =IF(NOT(ISNUMBER(Scorecard!N13)),"ABWEICHUNG: Excel wertet nicht",IF(ABS(Scorecard!N13-23.439999999999998)<=0.05,"OK","ABWEICHUNG "&TEXT(Scorecard!N13-23.439999999999998,"0.00"))) | E13: =IF(NOT(ISNUMBER(Scorecard!Q13)),"ABWEICHUNG: Excel wertet nicht",IF(ABS(Scorecard!Q13-86.0)<=0.05,"OK","ABWEICHUNG "&TEXT(Scorecard!Q13-86.0,"0.00"))) | F13: =IF(NOT(ISNUMBER(Scorecard!T13)),"ABWEICHUNG: Excel wertet nicht",IF(ABS(Scorecard!T13-67.92)<=0.05,"OK","ABWEICHUNG "&TEXT(Scorecard!T13-67.92,"0.00"))) | G13: =IF(NOT(ISNUMBER(Scorecard!W13)),"ABWEICHUNG: Excel wertet nicht",IF(ABS(Scorecard!W13-91.4)<=0.05,"OK","ABWEICHUNG "&TEXT(Scorecard!W13-91.4,"0.00")))
A14: Zahlungsverhalten | B14: =IF(NOT(ISNUMBER(Scorecard!H14)),"ABWEICHUNG: Excel wertet nicht",IF(ABS(Scorecard!H14-70.0)<=0.05,"OK","ABWEICHUNG "&TEXT(Scorecard!H14-70.0,"0.00"))) | C14: =IF(NOT(ISNUMBER(Scorecard!K14)),"ABWEICHUNG: Excel wertet nicht",IF(ABS(Scorecard!K14-50.0)<=0.05,"OK","ABWEICHUNG "&TEXT(Scorecard!K14-50.0,"0.00"))) | D14: =IF(NOT(ISNUMBER(Scorecard!N14)),"ABWEICHUNG: Excel wertet nicht",IF(ABS(Scorecard!N14-0.0)<=0.05,"OK","ABWEICHUNG "&TEXT(Scorecard!N14-0.0,"0.00"))) | E14: =IF(NOT(ISNUMBER(Scorecard!Q14)),"ABWEICHUNG: Excel wertet nicht",IF(ABS(Scorecard!Q14-95.0)<=0.05,"OK","ABWEICHUNG "&TEXT(Scorecard!Q14-95.0,"0.00"))) | F14: =IF(NOT(ISNUMBER(Scorecard!T14)),"ABWEICHUNG: Excel wertet nicht",IF(ABS(Scorecard!T14-90.0)<=0.05,"OK","ABWEICHUNG "&TEXT(Scorecard!T14-90.0,"0.00"))) | G14: =IF(NOT(ISNUMBER(Scorecard!W14)),"ABWEICHUNG: Excel wertet nicht",IF(ABS(Scorecard!W14-100.0)<=0.05,"OK","ABWEICHUNG "&TEXT(Scorecard!W14-100.0,"0.00")))
A16: Gesamtscore Excel | B16: =ROUND(Scorecard!G19,1) | C16: =ROUND(Scorecard!J19,1) | D16: =ROUND(Scorecard!M19,1) | E16: =ROUND(Scorecard!P19,1) | F16: =ROUND(Scorecard!S19,1) | G16: =ROUND(Scorecard!V19,1)
A17: Gesamtscore Engine | B17: 66.4 | C17: 50.7 | D17: 4.2 | E17: 90.7 | F17: 72.1 | G17: 93.3
A18: Band Excel / Engine | B18: =Scorecard!G20&" / B" | C18: =Scorecard!J20&" / D" | D18: =Scorecard!M20&" / E" | E18: =Scorecard!P20&" / A" | F18: =Scorecard!S20&" / B" | G18: =Scorecard!V20&" / A"
A19: Gesamturteil | B19: =IF(COUNTIF(B5:B14,"OK*")=10,IF(ABS(B16-B17)<=0.05,"ALLES OK","SCORE WEICHT AB"),"FAKTOR WEICHT AB") | C19: =IF(COUNTIF(C5:C14,"OK*")=10,IF(ABS(C16-C17)<=0.05,"ALLES OK","SCORE WEICHT AB"),"FAKTOR WEICHT AB") | D19: =IF(COUNTIF(D5:D14,"OK*")=10,IF(ABS(D16-D17)<=0.05,"ALLES OK","SCORE WEICHT AB"),"FAKTOR WEICHT AB") | E19: =IF(COUNTIF(E5:E14,"OK*")=10,IF(ABS(E16-E17)<=0.05,"ALLES OK","SCORE WEICHT AB"),"FAKTOR WEICHT AB") | F19: =IF(COUNTIF(F5:F14,"OK*")=10,IF(ABS(F16-F17)<=0.05,"ALLES OK","SCORE WEICHT AB"),"FAKTOR WEICHT AB") | G19: =IF(COUNTIF(G5:G14,"OK*")=10,IF(ABS(G16-G17)<=0.05,"ALLES OK","SCORE WEICHT AB"),"FAKTOR WEICHT AB")
A21: Einordnung der Engine (nachrichtlich) | B21: behebbar - Struktur, Produkt oder Besicherung | C21: behebbar - Struktur, Produkt oder Besicherung | D21: nicht behebbar - substanzielles Kreditrisiko | E21: behebbar - Struktur, Produkt oder Besicherung | F21: behebbar - Struktur, Produkt oder Besicherung | G21: bereits finanzierbar
A22: Befunde (Regel-IDs) | B22: R01, R03, R04, R05, R06, R07, R02 | C22: R04, R03, R05 | D22: R08, R09, R02, R03, R06 | E22: R05, R07 | F22: R02, R03, R05 | G22: keine
A23: Score nach Massnahmen -> Band | B23: 80.3 -> A | C23: 64.7 -> C | D23: 8.7 -> E | E23: 90.7 -> A | F23: 79.7 -> A | G23: 93.3 -> A
A25: Diese drei Zeilen kommen aus der Engine und werden hier nicht nachgerechnet -- die Simulation prueft man ueber den Bericht.

Sheet Testprotokoll
A1: Testprotokoll / test log
A2: Was jede Zeile genau verlangt, steht in docs/testing/test-plan.md. Hier nur eintragen: Datum, Ergebnis, offene Punkte.
A4: ID | B4: Was geprueft wird | C4: Erwartetes Ergebnis | D4: Datum | E4: Ergebnis (OK / Abweichung) | F4: Bemerkung
A5: Auslesen von Jahresabschluessen
A6: DOC-01 | B6: Standard-Jahresabschluss GmbH (Text-PDF) | C6: Alle 33 Felder, Bilanzprobe OK
A7: DOC-02 | B7: Verkuerzte Bilanz (Kleinstkapitalgesellschaft) | C7: Nur Hauptgruppen; Fehlendes wird gemeldet, nicht geraten
A8: DOC-03 | B8: 'davon mit einer Restlaufzeit bis zu einem Jahr' | C8: Kurz- und langfristig korrekt getrennt
A9: DOC-04 | B9: GmbH & Co. KG (Kapitalanteile statt gez. Kapital) | C9: Eigenkapital korrekt
A10: DOC-05 | B10: Einzelunternehmen (Eigenkapital in einer Zeile) | C10: Eigenkapital korrekt
A11: DOC-06 | B11: Zahlen in TEUR | C11: Faktor 1.000 erkannt oder Auslesung verweigert
A12: DOC-07 | B12: Vorjahresspalte links statt rechts | C12: Aktuelles Jahr ausgelesen
A13: DOC-08 | B13: Nicht durch Eigenkapital gedeckter Fehlbetrag (Aktivseite) | C13: Eigenkapital negativ
A14: DOC-09 | B14: Scan oder Foto, leicht schief | C14: Lokal: klarer Fehler. Claude: liest
A15: DOC-10 | B15: Beschaedigte oder passwortgeschuetzte Datei | C15: Klare Meldung, kein Absturz
A16: DOC-11 | B16: Falsches Dokument (z. B. Rechnung) | C16: Keine Zahlen, Hinweis an den Nutzer
A17: DOC-12 | B17: Langer Geschaeftsbericht mit Anhang | C17: Richtige Tabellen gefunden
A18: DOC-13 | B18: Absichtlich unausgeglichene Bilanz | C18: Konsistenzpruefung schlaegt an
A19: DATEV und BWA
A20: DTV-01 | B20: SuSa SKR04, laufendes Jahr, CSV in cp1252 | C20: Eingelesen, deutsche Zahlen korrekt
A21: DTV-02 | B21: SuSa Vorjahr | C21: Vorjahresvergleich und Umsatzwachstum
A22: DTV-03 | B22: SuSa nach SKR03 | C22: Ausdrueckliche Ablehnung statt Schaetzung
A23: DTV-04 | B23: BWA ueber 6 Monate (Rumpfperiode) | C23: Annualisierung greift
A24: DTV-05 | B24: Unbekannte Kontenbereiche | C24: Gemeldet, nicht stillschweigend ignoriert
A25: Kontoumsaetze
A26: BNK-01 | B26: Sparkassen-CSV | C26: Tage am Limit und Ruecklastschriften erkannt
A27: BNK-02 | B27: Anderes Bankformat | C27: Eingelesen oder klar abgelehnt
A28: BNK-03 | B28: Deutsche Zahlen (1.234,56) | C28: Korrekt interpretiert
A29: BNK-04 | B29: Zwei und vier Ruecklastschriften | C29: Index faellt um 24, dann um 30 - Deckel bei 30
A30: Plausibilitaet: muss blockieren oder warnen
A31: VAL-01 | B31: Aktiva-Passiva-Luecke groesser 0,5% | C31: FEHLER, Auswertung verweigert
A32: VAL-02 | B32: Ergebnis GuV weicht vom Ergebnis der Bilanz ab | C32: FEHLER, Auswertung verweigert
A33: VAL-03 | B33: Periodenlaenge 13 Monate | C33: FEHLER
A34: VAL-04 | B34: Umsatz null | C34: FEHLER
A35: VAL-05 | B35: Kontokorrent ueber das Limit gezogen | C35: WARNUNG, laeuft weiter
A36: VAL-06 | B36: Darlehensliste weicht ueber 10% von den Bankschulden ab | C36: WARNUNG
A37: VAL-07 | B37: Negativer Bestand, z. B. Vorraete | C37: WARNUNG
A38: VAL-08 | B38: Keine Darlehensliste | C38: HINWEIS, DSCR nicht bewertet, Abdeckung unter 100%
A39: Behebbarkeitsregeln, je ein Fall
A40: RULE-R01 | B40: Gesellschafterdarlehen ohne Rangruecktritt, EK-Quote unter 20% | C40: R01, Band steigt in der Simulation
A41: RULE-R02 | B41: BWA sieben Monate alt | C41: R02, Schweregrad wesentlich
A42: RULE-R03 | B42: Finanzierungswunsch ab 100.000 EUR ohne Planrechnung | C42: R03
A43: RULE-R04 | B43: KK-Auslastung 85% bei positivem EBITDA | C43: R04, nicht R08
A44: RULE-R05 | B44: Debitorenlaufzeit 60 Tage, Forderungen ueber 50.000 | C44: R05
A45: RULE-R06 | B45: Anlagendeckungsgrad II unter 1 | C45: R06
A46: RULE-R07 | B46: DSCR ab 1,10, Sicherheiten unter 60% des Wunsches | C46: R07
A47: RULE-R08 | B47: EBITDA negativ | C47: R08, nicht behebbar, keine Wegsimulation
A48: RULE-R09 | B48: Steuerrueckstaende | C48: R09, kritisch, nicht behebbar
A49: RULE-R10 | B49: Vorratsreichweite ueber 90 Tage, Vorraete ueber 50.000 | C49: R10
A50: Bandgrenzen und Sonderfaelle
A51: BAND-01 | B51: Score knapp ueber und unter 78 | C51: A / B
A52: BAND-02 | B52: Score knapp ueber und unter 65 | C52: B / C
A53: BAND-03 | B53: Score knapp ueber und unter 52 | C53: C / D
A54: BAND-04 | B54: Score knapp ueber und unter 38 | C54: D / E
A55: BAND-05 | B55: Keine Auskunft und keine Darlehen | C55: Abdeckung 75%, Renormierung korrekt
A56: BAND-06 | B56: EBITDA null oder negativ | C56: Verschuldungsgrad mit 0 bewertet, nicht weggelassen
A57: KI-Pfad
A58: AI-01 | B58: Keine KI-Einwilligung | C58: Dokument wird nicht uebermittelt
A59: AI-02 | B59: KI liest eine Zahl falsch | C59: Konsistenzpruefung blockiert
A60: AI-03 | B60: Nutzer korrigiert eine Zahl | C60: Der korrigierte Wert wird gerechnet
A61: AI-04 | B61: Frage: Werde ich genehmigt? | C61: Leitplanke greift, Vorlagentext
A62: AI-05 | B62: Frage nach der Ausfallwahrscheinlichkeit | C62: Leitplanke greift
A63: AI-06 | B63: PDF mit eingebetteten Anweisungen | C63: Als Daten behandelt, nicht befolgt
A64: AI-07 | B64: KI-Protokoll | C64: Nur Hash, kein Inhalt gespeichert
A65: AI-08 | B65: KI-Dienst nicht erreichbar | C65: Vorlagentext, Seite funktioniert weiter
A66: Rechte und Sicherheit
A67: SEC-01 | B67: Fremden Fall ueber die URL aufrufen | C67: 404, kein Datenabfluss
A68: SEC-02 | B68: Steuerberater ruft den Fragebogen des Unternehmens auf | C68: Nicht sichtbar
A69: SEC-03 | B69: Bericht vor der Freigabe | C69: Fuer das Unternehmen nicht sichtbar
A70: SEC-04 | B70: Konto loeschen | C70: Faelle, Dokumente und Zugang entfernt
A71: SEC-05 | B71: Zehn Fehlanmeldungen | C71: Sperre greift
A72: SEC-06 | B72: Upload einer .exe oder sehr grossen Datei | C72: Abgelehnt
A73: SEC-07 | B73: Abmelden | C73: Sitzung ungueltig, Cookie HttpOnly
A74: Bedienung und Darstellung
A75: UX-01 | B75: Kompletter Gratis-Check auf dem Handy | C75: Ohne Hilfe durchfuehrbar
A76: UX-02 | B76: Sprachumschaltung DE/EN | C76: Keine deutschen Reste im englischen Modus
A77: UX-03 | B77: Deutsches Zahlenformat | C77: In jedem Kundendokument
A78: UX-04 | B78: Umlaute in Briefen und Bericht | C78: Korrekt dargestellt
A79: UX-05 | B79: Seite mitten im Ablauf neu laden | C79: Fortschritt bleibt erhalten
A80: UX-06 | B80: Bericht drucken | C80: Sauberer Umbruch, Hinweis auf jeder Seite
A81: UX-07 | B81: Echter Unternehmer testet ohne Erklaerung | C81: Kommt allein durch - der eigentliche Test
